[{"title": "Muchas Cosas Cambian Parte 1", "season": "1", "chapter": "1", "description": "", "href": "https://clasico.tv/episodes/ben-10-omniverse-1x1/", "sources": ["//sendvid.com/embed/yuc3v4k6"]}, {"title": "Muchas Cosas Cambian Parte 2", "season": "1", "chapter": "2", "description": "", "href": "https://clasico.tv/episodes/ben-10-omniverse-1x2/", "sources": ["//sendvid.com/embed/yuc3v4k6"]}, {"title": "Una Sacudida del Pasado", "season": "1", "chapter": "3", "description": "", "href": "https://clasico.tv/episodes/ben-10-omniverse-1x3/", "sources": ["//sendvid.com/embed/yuc3v4k6"]}, {"title": "H\u00e9lix Problem\u00e1tico", "season": "1", "chapter": "4", "description": "", "href": "https://clasico.tv/episodes/ben-10-omniverse-1x4/", "sources": ["//sendvid.com/embed/yuc3v4k6"]}, {"title": "Hagamos un Trato", "season": "1", "chapter": "5", "description": "", "href": "https://clasico.tv/episodes/ben-10-omniverse-1x5/", "sources": ["//sendvid.com/embed/yuc3v4k6"]}, {"title": "Fueron Ellos", "season": "1", "chapter": "6", "description": "", "href": "https://clasico.tv/episodes/ben-10-omniverse-1x6/", "sources": ["//sendvid.com/embed/yuc3v4k6"]}, {"title": "Adi\u00f3s y Gracias por Todos los Smoothies", "season": "1", "chapter": "7", "description": "", "href": "https://clasico.tv/episodes/ben-10-omniverse-1x7/", "sources": ["//sendvid.com/embed/yuc3v4k6"]}, {"title": "Punto Caliente", "season": "1", "chapter": "8", "description": "", "href": "https://clasico.tv/episodes/ben-10-omniverse-1x8/", "sources": ["//sendvid.com/embed/yuc3v4k6"]}, {"title": "Depredadores y Presa Parte 1", "season": "1", "chapter": "9", "description": "", "href": "https://clasico.tv/episodes/ben-10-omniverse-1x9/", "sources": ["//sendvid.com/embed/yuc3v4k6"]}, {"title": "Depredadores y Presa Parte 2", "season": "1", "chapter": "10", "description": "", "href": "https://clasico.tv/episodes/ben-10-omniverse-1x10/", "sources": ["//sendvid.com/embed/yuc3v4k6"]}, {"title": "Estallido", "season": "2", "chapter": "1", "description": "", "href": "https://clasico.tv/episodes/ben-10-omniverse-2x1/", "sources": ["//sendvid.com/embed/yuc3v4k6"]}, {"title": "Muchos regresos felices", "season": "2", "chapter": "2", "description": "", "href": "https://clasico.tv/episodes/ben-10-omniverse-2x2/", "sources": ["//sendvid.com/embed/yuc3v4k6"]}, {"title": "De Pesca", "season": "2", "chapter": "3", "description": "", "href": "https://clasico.tv/episodes/ben-10-omniverse-2x3/", "sources": ["//sendvid.com/embed/yuc3v4k6"]}, {"title": "Blukic y Driba Visitan al Sr. Smoothies", "season": "2", "chapter": "4", "description": "", "href": "https://clasico.tv/episodes/ben-10-omniverse-2x4/", "sources": ["//sendvid.com/embed/yuc3v4k6"]}, {"title": "Factor Malware", "season": "2", "chapter": "5", "description": "", "href": "https://clasico.tv/episodes/ben-10-omniverse-2x5/", "sources": ["//sendvid.com/embed/yuc3v4k6"]}, {"title": "Desarrollo Suspendido", "season": "2", "chapter": "6", "description": "", "href": "https://clasico.tv/episodes/ben-10-omniverse-2x6/", "sources": ["//sendvid.com/embed/yuc3v4k6"]}, {"title": "Hermanos en el espacio", "season": "2", "chapter": "7", "description": "", "href": "https://clasico.tv/episodes/ben-10-omniverse-2x7/", "sources": ["//sendvid.com/embed/yuc3v4k6"]}, {"title": "Ben otra vez", "season": "2", "chapter": "8", "description": "", "href": "https://clasico.tv/episodes/ben-10-omniverse-2x8/", "sources": ["//sendvid.com/embed/yuc3v4k6"]}, {"title": "Confrontaci\u00f3n Parte 1", "season": "2", "chapter": "9", "description": "", "href": "https://clasico.tv/episodes/ben-10-omniverse-2x9/", "sources": ["//sendvid.com/embed/yuc3v4k6"]}, {"title": "Confrontaci\u00f3n Parte 2", "season": "2", "chapter": "10", "description": "", "href": "https://clasico.tv/episodes/ben-10-omniverse-2x10/", "sources": ["//sendvid.com/embed/yuc3v4k6"]}, {"title": "Tienda 23", "season": "3", "chapter": "1", "description": "", "href": "https://clasico.tv/episodes/ben-10-omniverse-3x1/", "sources": ["//sendvid.com/embed/yuc3v4k6"]}, {"title": "Entrega Especial", "season": "3", "chapter": "2", "description": "", "href": "https://clasico.tv/episodes/ben-10-omniverse-3x2/", "sources": ["//sendvid.com/embed/yuc3v4k6"]}, {"title": "Problemas Estomacales", "season": "3", "chapter": "3", "description": "", "href": "https://clasico.tv/episodes/ben-10-omniverse-3x3/", "sources": ["//sendvid.com/embed/yuc3v4k6"]}, {"title": "Vilgax Debe Morir", "season": "3", "chapter": "4", "description": "", "href": "https://clasico.tv/episodes/ben-10-omniverse-3x4/", "sources": ["//sendvid.com/embed/yuc3v4k6"]}, {"title": "Mientras Estabas Lejos", "season": "3", "chapter": "5", "description": "", "href": "https://clasico.tv/episodes/ben-10-omniverse-3x5/", "sources": ["//sendvid.com/embed/yuc3v4k6"]}, {"title": "Las Reglas del Compromiso", "season": "3", "chapter": "6", "description": "", "href": "https://clasico.tv/episodes/ben-10-omniverse-3x6/", "sources": ["//sendvid.com/embed/yuc3v4k6"]}, {"title": "Rad", "season": "3", "chapter": "7", "description": "", "href": "https://clasico.tv/episodes/ben-10-omniverse-3x7/", "sources": ["//sendvid.com/embed/yuc3v4k6"]}, {"title": "La Reuni\u00f3n del Mal", "season": "3", "chapter": "8", "description": "", "href": "https://clasico.tv/episodes/ben-10-omniverse-3x8/", "sources": ["//sendvid.com/embed/yuc3v4k6"]}, {"title": "Gracias a Dios son los S\u00e1bados Secretos", "season": "3", "chapter": "9", "description": "", "href": "https://clasico.tv/episodes/ben-10-omniverse-3x9/", "sources": ["//sendvid.com/embed/yuc3v4k6"]}, {"title": "Comida a la Vuelta de la Esquina", "season": "3", "chapter": "10", "description": "", "href": "https://clasico.tv/episodes/ben-10-omniverse-3x10/", "sources": ["//sendvid.com/embed/yuc3v4k6"]}, {"title": "Oh Mam\u00e1, \u00bfD\u00f3nde Est\u00e1s?", "season": "4", "chapter": "1", "description": "", "href": "https://clasico.tv/episodes/ben-10-omniverse-4x1/", "sources": ["//sendvid.com/embed/yuc3v4k6"]}, {"title": "Las ranas de la guerra Parte 1", "season": "4", "chapter": "2", "description": "", "href": "https://clasico.tv/episodes/ben-10-omniverse-4x2/", "sources": ["//sendvid.com/embed/yuc3v4k6"]}, {"title": "Las ranas de la guerra Parte 2", "season": "4", "chapter": "3", "description": "", "href": "https://clasico.tv/episodes/ben-10-omniverse-4x3/", "sources": ["//sendvid.com/embed/yuc3v4k6"]}, {"title": "El Regreso de los Eternos", "season": "4", "chapter": "4", "description": "", "href": "https://clasico.tv/episodes/ben-10-omniverse-4x4/", "sources": ["//sendvid.com/embed/yuc3v4k6"]}, {"title": "El Lodo es m\u00e1s Denso que el Agua", "season": "4", "chapter": "5", "description": "", "href": "https://clasico.tv/episodes/ben-10-omniverse-4x5/", "sources": ["//sendvid.com/embed/yuc3v4k6"]}, {"title": "Los Motivos de OTTO", "season": "4", "chapter": "6", "description": "", "href": "https://clasico.tv/episodes/ben-10-omniverse-4x6/", "sources": ["//sendvid.com/embed/yuc3v4k6"]}, {"title": "El M\u00e1ximo Atraco", "season": "4", "chapter": "7", "description": "", "href": "https://clasico.tv/episodes/ben-10-omniverse-4x7/", "sources": ["//sendvid.com/embed/yuc3v4k6"]}, {"title": "Un Pu\u00f1ado de Cerebros", "season": "4", "chapter": "8", "description": "", "href": "https://clasico.tv/episodes/ben-10-omniverse-4x8/", "sources": ["//sendvid.com/embed/yuc3v4k6"]}, {"title": "El Monstruo de Max", "season": "4", "chapter": "9", "description": "", "href": "https://clasico.tv/episodes/ben-10-omniverse-4x9/", "sources": ["//sendvid.com/embed/yuc3v4k6"]}, {"title": "Por un Par de Cerebros M\u00e1s", "season": "4", "chapter": "10", "description": "", "href": "https://clasico.tv/episodes/ben-10-omniverse-4x10/", "sources": ["//sendvid.com/embed/yuc3v4k6"]}, {"title": "Algo Zombozo se Aproxima", "season": "5", "chapter": "1", "description": "", "href": "https://clasico.tv/episodes/ben-10-omniverse-5x1/", "sources": ["//sendvid.com/embed/yuc3v4k6"]}, {"title": "Misterio Incorp\u00f3reo", "season": "5", "chapter": "2", "description": "", "href": "https://clasico.tv/episodes/ben-10-omniverse-5x2/", "sources": ["//sendvid.com/embed/yuc3v4k6"]}, {"title": "La Venganza es M\u00eda", "season": "5", "chapter": "3", "description": "", "href": "https://clasico.tv/episodes/ben-10-omniverse-5x3/", "sources": ["//sendvid.com/embed/yuc3v4k6"]}, {"title": "Un Benlobo Americano en Londres", "season": "5", "chapter": "4", "description": "", "href": "https://clasico.tv/episodes/ben-10-omniverse-5x4/", "sources": ["//sendvid.com/embed/yuc3v4k6"]}, {"title": "Mis Dos Doctores", "season": "5", "chapter": "5", "description": "", "href": "https://clasico.tv/episodes/ben-10-omniverse-5x5/", "sources": ["//sendvid.com/embed/yuc3v4k6"]}, {"title": "La Fiesta de los Monstruos", "season": "5", "chapter": "6", "description": "", "href": "https://clasico.tv/episodes/ben-10-omniverse-5x6/", "sources": ["//sendvid.com/embed/yuc3v4k6"]}, {"title": "Chamcaster Regresa", "season": "5", "chapter": "7", "description": "", "href": "https://clasico.tv/episodes/ben-10-omniverse-5x7/", "sources": ["//sendvid.com/embed/yuc3v4k6"]}, {"title": "El Vampiro Contraataca", "season": "5", "chapter": "8", "description": "", "href": "https://clasico.tv/episodes/ben-10-omniverse-5x8/", "sources": ["//sendvid.com/embed/yuc3v4k6"]}, {"title": "El Principio del \u00daltimo", "season": "5", "chapter": "9", "description": "", "href": "https://clasico.tv/episodes/ben-10-omniverse-5x9/", "sources": ["//sendvid.com/embed/yuc3v4k6"]}, {"title": "Y Al Final Qued\u00f3 Ben", "season": "5", "chapter": "10", "description": "", "href": "https://clasico.tv/episodes/ben-10-omniverse-5x10/", "sources": ["//sendvid.com/embed/yuc3v4k6"]}, {"title": "Tri\u00e1ngulo Amoroso", "season": "6", "chapter": "1", "description": "", "href": "https://clasico.tv/episodes/ben-10-omniverse-6x1/", "sources": ["//sendvid.com/embed/yuc3v4k6"]}, {"title": "Colecciona Esto", "season": "6", "chapter": "2", "description": "", "href": "https://clasico.tv/episodes/ben-10-omniverse-6x2/", "sources": ["//sendvid.com/embed/yuc3v4k6"]}, {"title": "Los Vengers", "season": "6", "chapter": "3", "description": "", "href": "https://clasico.tv/episodes/ben-10-omniverse-6x3/", "sources": ["//sendvid.com/embed/yuc3v4k6"]}, {"title": "Devu\u00e9lvelo", "season": "6", "chapter": "4", "description": "", "href": "https://clasico.tv/episodes/ben-10-omniverse-6x4/", "sources": ["//sendvid.com/embed/yuc3v4k6"]}, {"title": "Las Ra\u00edces del Mal", "season": "6", "chapter": "5", "description": "", "href": "https://clasico.tv/episodes/ben-10-omniverse-6x5/", "sources": ["//sendvid.com/embed/yuc3v4k6"]}, {"title": "Blukic y Driba van al \u00c1rea 51", "season": "6", "chapter": "6", "description": "", "href": "https://clasico.tv/episodes/ben-10-omniverse-6x6/", "sources": ["//sendvid.com/embed/yuc3v4k6"]}, {"title": "No Hay Honor Entre Hermanos", "season": "6", "chapter": "7", "description": "", "href": "https://clasico.tv/episodes/ben-10-omniverse-6x7/", "sources": ["//sendvid.com/embed/yuc3v4k6"]}, {"title": "El Universo Vs. Tennyson", "season": "6", "chapter": "8", "description": "", "href": "https://clasico.tv/episodes/ben-10-omniverse-6x8/", "sources": ["//sendvid.com/embed/yuc3v4k6"]}, {"title": "Arma 11 Parte 1", "season": "6", "chapter": "9", "description": "", "href": "https://clasico.tv/episodes/ben-10-omniverse-6x9/", "sources": ["//sendvid.com/embed/yuc3v4k6"]}, {"title": "Arma 11 Parte 2", "season": "6", "chapter": "10", "description": "", "href": "https://clasico.tv/episodes/ben-10-omniverse-6x10/", "sources": ["//sendvid.com/embed/yuc3v4k6"]}, {"title": "Clyde 5", "season": "7", "chapter": "1", "description": "", "href": "https://clasico.tv/episodes/ben-10-omniverse-7x1/", "sources": ["//sendvid.com/embed/yuc3v4k6"]}, {"title": "Los Rook", "season": "7", "chapter": "2", "description": "", "href": "https://clasico.tv/episodes/ben-10-omniverse-7x2/", "sources": ["//sendvid.com/embed/yuc3v4k6"]}, {"title": "Escuela de Encantos", "season": "7", "chapter": "3", "description": "", "href": "https://clasico.tv/episodes/ben-10-omniverse-7x3/", "sources": ["//sendvid.com/embed/yuc3v4k6"]}, {"title": "La Balada del Sr. Baumann", "season": "7", "chapter": "4", "description": "", "href": "https://clasico.tv/episodes/ben-10-omniverse-7x4/", "sources": ["//sendvid.com/embed/yuc3v4k6"]}, {"title": "Una Pelea en el Museo", "season": "7", "chapter": "5", "description": "", "href": "https://clasico.tv/episodes/ben-10-omniverse-7x5/", "sources": ["//sendvid.com/embed/yuc3v4k6"]}, {"title": "Punto de Quiebra", "season": "7", "chapter": "6", "description": "", "href": "https://clasico.tv/episodes/ben-10-omniverse-7x6/", "sources": ["//sendvid.com/embed/yuc3v4k6"]}, {"title": "El Color del Simio", "season": "7", "chapter": "7", "description": "", "href": "https://clasico.tv/episodes/ben-10-omniverse-7x7/", "sources": ["//sendvid.com/embed/yuc3v4k6"]}, {"title": "Vreedleman\u00eda", "season": "7", "chapter": "8", "description": "", "href": "https://clasico.tv/episodes/ben-10-omniverse-7x8/", "sources": ["//sendvid.com/embed/yuc3v4k6"]}, {"title": "El Mundo de Ben Est\u00e1 Loco, Loco, Loco Parte 1", "season": "7", "chapter": "9", "description": "", "href": "https://clasico.tv/episodes/ben-10-omniverse-7x9/", "sources": ["//sendvid.com/embed/yuc3v4k6"]}, {"title": "El Mundo de Ben Est\u00e1 Loco, Loco, Loco Parte 2", "season": "7", "chapter": "10", "description": "", "href": "https://clasico.tv/episodes/ben-10-omniverse-7x10/", "sources": ["//sendvid.com/embed/yuc3v4k6"]}, {"title": "Del Hedorio a la Eternidad", "season": "8", "chapter": "1", "description": "", "href": "https://clasico.tv/episodes/ben-10-omniverse-8x1/", "sources": ["//sendvid.com/embed/yuc3v4k6"]}, {"title": "Pegado a Ti", "season": "8", "chapter": "2", "description": "", "href": "https://clasico.tv/episodes/ben-10-omniverse-8x2/", "sources": ["//sendvid.com/embed/yuc3v4k6"]}, {"title": "El Baile del Tiempo", "season": "8", "chapter": "3", "description": "", "href": "https://clasico.tv/episodes/ben-10-omniverse-8x3/", "sources": ["//sendvid.com/embed/yuc3v4k6"]}, {"title": "Secreto de Dos Santos", "season": "8", "chapter": "4", "description": "", "href": "https://clasico.tv/episodes/ben-10-omniverse-8x4/", "sources": ["//sendvid.com/embed/yuc3v4k6"]}, {"title": "Charmcaster Regresa", "season": "8", "chapter": "5", "description": "", "href": "https://clasico.tv/episodes/ben-10-omniverse-8x5/", "sources": ["//sendvid.com/embed/yuc3v4k6"]}, {"title": "El Conteo Final", "season": "8", "chapter": "6", "description": "", "href": "https://clasico.tv/episodes/ben-10-omniverse-8x6/", "sources": ["//sendvid.com/embed/yuc3v4k6"]}, {"title": "Malgax Ataca", "season": "8", "chapter": "7", "description": "", "href": "https://clasico.tv/episodes/ben-10-omniverse-8x7/", "sources": ["//sendvid.com/embed/yuc3v4k6"]}, {"title": "El Juego M\u00e1s Peligroso", "season": "8", "chapter": "8", "description": "", "href": "https://clasico.tv/episodes/ben-10-omniverse-8x8/", "sources": ["//sendvid.com/embed/yuc3v4k6"]}, {"title": "El Final de una Era", "season": "8", "chapter": "9", "description": "", "href": "https://clasico.tv/episodes/ben-10-omniverse-8x9/", "sources": ["//sendvid.com/embed/yuc3v4k6"]}, {"title": "Un Nuevo Amanecer", "season": "8", "chapter": "10", "description": "", "href": "https://clasico.tv/episodes/ben-10-omniverse-8x10/", "sources": ["//sendvid.com/embed/yuc3v4k6"]}]