[{"title": "Piloto", "season": "1", "chapter": "1", "description": "", "href": "https://clasico.tv/episodes/clarence-1x1/", "sources": ["//sendvid.com/embed/yuc3v4k6"]}, {"title": "Enfrentamiento En El Calabozo Divertido ", "season": "1", "chapter": "2", "description": "", "href": "https://clasico.tv/episodes/clarence-1x2/", "sources": ["//sendvid.com/embed/yuc3v4k6"]}, {"title": "Un D\u00eda Genial Con Una Chica", "season": "1", "chapter": "3", "description": "", "href": "https://clasico.tv/episodes/clarence-1x3/", "sources": ["//sendvid.com/embed/yuc3v4k6"]}, {"title": "El Mago Del Videojuego", "season": "1", "chapter": "4", "description": "", "href": "https://clasico.tv/episodes/clarence-1x4/", "sources": ["//sendvid.com/embed/yuc3v4k6"]}, {"title": "Perdido En El Supermercado", "season": "1", "chapter": "5", "description": "", "href": "https://clasico.tv/episodes/clarence-1x5/", "sources": ["//sendvid.com/embed/yuc3v4k6"]}, {"title": "Los Millones De Clarence", "season": "1", "chapter": "6", "description": "", "href": "https://clasico.tv/episodes/clarence-1x6/", "sources": ["//sendvid.com/embed/yuc3v4k6"]}, {"title": "Clarence Consigue Una Novia", "season": "1", "chapter": "7", "description": "", "href": "https://clasico.tv/episodes/clarence-1x7/", "sources": ["//sendvid.com/embed/yuc3v4k6"]}, {"title": "El Juguete Nuevo De Jeff", "season": "1", "chapter": "8", "description": "", "href": "https://clasico.tv/episodes/clarence-1x8/", "sources": ["//sendvid.com/embed/yuc3v4k6"]}, {"title": "La Cena ", "season": "1", "chapter": "9", "description": "", "href": "https://clasico.tv/episodes/clarence-1x9/", "sources": ["//sendvid.com/embed/yuc3v4k6"]}, {"title": "Bocinazo ", "season": "1", "chapter": "10", "description": "", "href": "https://clasico.tv/episodes/clarence-1x10/", "sources": ["//sendvid.com/embed/yuc3v4k6"]}, {"title": "La B\u00fasqueda Del D\u00f3lar", "season": "1", "chapter": "11", "description": "", "href": "https://clasico.tv/episodes/clarence-1x11/", "sources": ["//sendvid.com/embed/yuc3v4k6"]}, {"title": "El Zool\u00f3gico", "season": "1", "chapter": "12", "description": "", "href": "https://clasico.tv/episodes/clarence-1x12/", "sources": ["//sendvid.com/embed/yuc3v4k6"]}, {"title": "A Levantarse", "season": "1", "chapter": "13", "description": "", "href": "https://clasico.tv/episodes/clarence-1x13/", "sources": ["//sendvid.com/embed/yuc3v4k6"]}, {"title": "El Hombre De La Casa", "season": "1", "chapter": "14", "description": "", "href": "https://clasico.tv/episodes/clarence-1x14/", "sources": ["//sendvid.com/embed/yuc3v4k6"]}, {"title": "Ojos Enlodados", "season": "1", "chapter": "15", "description": "", "href": "https://clasico.tv/episodes/clarence-1x15/", "sources": ["//sendvid.com/embed/yuc3v4k6"]}, {"title": "El Bote So\u00f1ado", "season": "1", "chapter": "16", "description": "", "href": "https://clasico.tv/episodes/clarence-1x16/", "sources": ["//sendvid.com/embed/yuc3v4k6"]}, {"title": "Pijamada ", "season": "1", "chapter": "17", "description": "", "href": "https://clasico.tv/episodes/clarence-1x17/", "sources": ["//sendvid.com/embed/yuc3v4k6"]}, {"title": "Clarence De La Selva", "season": "1", "chapter": "18", "description": "", "href": "https://clasico.tv/episodes/clarence-1x18/", "sources": ["//sendvid.com/embed/yuc3v4k6"]}, {"title": "Un Jeff Corriente", "season": "1", "chapter": "19", "description": "", "href": "https://clasico.tv/episodes/clarence-1x19/", "sources": ["//sendvid.com/embed/yuc3v4k6"]}, {"title": "El D\u00eda De La Lagartija", "season": "1", "chapter": "20", "description": "", "href": "https://clasico.tv/episodes/clarence-1x20/", "sources": ["//sendvid.com/embed/yuc3v4k6"]}, {"title": "Los Olvidados", "season": "1", "chapter": "21", "description": "", "href": "https://clasico.tv/episodes/clarence-1x21/", "sources": ["//sendvid.com/embed/yuc3v4k6"]}, {"title": "La Barbacoa del Vecindario", "season": "1", "chapter": "22", "description": "", "href": "https://clasico.tv/episodes/clarence-1x22/", "sources": ["//sendvid.com/embed/yuc3v4k6"]}, {"title": "Pijamada En Casa De Belson", "season": "1", "chapter": "23", "description": "", "href": "https://clasico.tv/episodes/clarence-1x23/", "sources": ["//sendvid.com/embed/yuc3v4k6"]}, {"title": "Demasiado Asqueroso Para Ser C\u00f3modo", "season": "1", "chapter": "24", "description": "", "href": "https://clasico.tv/episodes/clarence-1x24/", "sources": ["//sendvid.com/embed/yuc3v4k6"]}, {"title": "Expansi\u00f3n Piloto", "season": "1", "chapter": "25", "description": "", "href": "https://clasico.tv/episodes/clarence-1x25/", "sources": ["//sendvid.com/embed/yuc3v4k6"]}, {"title": "Pacientes ", "season": "1", "chapter": "26", "description": "", "href": "https://clasico.tv/episodes/clarence-1x26/", "sources": ["//sendvid.com/embed/yuc3v4k6"]}, {"title": "Escuela Rough Riders", "season": "1", "chapter": "27", "description": "", "href": "https://clasico.tv/episodes/clarence-1x27/", "sources": ["//sendvid.com/embed/yuc3v4k6"]}, {"title": "Nada Atrevido", "season": "1", "chapter": "28", "description": "", "href": "https://clasico.tv/episodes/clarence-1x28/", "sources": ["//sendvid.com/embed/yuc3v4k6"]}, {"title": "Modales De Cabecera", "season": "1", "chapter": "29", "description": "", "href": "https://clasico.tv/episodes/clarence-1x29/", "sources": ["//sendvid.com/embed/yuc3v4k6"]}, {"title": "Jeff Gana ", "season": "1", "chapter": "30", "description": "", "href": "https://clasico.tv/episodes/clarence-1x30/", "sources": ["//sendvid.com/embed/yuc3v4k6"]}, {"title": "Suspendidos", "season": "1", "chapter": "31", "description": "", "href": "https://clasico.tv/episodes/clarence-1x31/", "sources": ["//sendvid.com/embed/yuc3v4k6"]}, {"title": "Sombreros De Tortuga", "season": "1", "chapter": "32", "description": "", "href": "https://clasico.tv/episodes/clarence-1x32/", "sources": ["//sendvid.com/embed/yuc3v4k6"]}, {"title": "La Persecuci\u00f3n Del Ganso", "season": "1", "chapter": "33", "description": "", "href": "https://clasico.tv/episodes/clarence-1x33/", "sources": ["//sendvid.com/embed/yuc3v4k6"]}, {"title": "Locuras De Pez Dorado", "season": "1", "chapter": "34", "description": "", "href": "https://clasico.tv/episodes/clarence-1x34/", "sources": ["//sendvid.com/embed/yuc3v4k6"]}, {"title": "Chimenea ", "season": "1", "chapter": "35", "description": "", "href": "https://clasico.tv/episodes/clarence-1x35/", "sources": ["//sendvid.com/embed/yuc3v4k6"]}, {"title": "Directo En Cama", "season": "1", "chapter": "36", "description": "", "href": "https://clasico.tv/episodes/clarence-1x36/", "sources": ["//sendvid.com/embed/yuc3v4k6"]}, {"title": "Compa\u00f1eros De Limpieza", "season": "1", "chapter": "37", "description": "", "href": "https://clasico.tv/episodes/clarence-1x37/", "sources": ["//sendvid.com/embed/yuc3v4k6"]}, {"title": "Hurac\u00e1n Dillis", "season": "1", "chapter": "38", "description": "", "href": "https://clasico.tv/episodes/clarence-1x38/", "sources": ["//sendvid.com/embed/yuc3v4k6"]}, {"title": "Sigue a la Cerda", "season": "1", "chapter": "39", "description": "", "href": "https://clasico.tv/episodes/clarence-1x39/", "sources": ["//sendvid.com/embed/yuc3v4k6"]}, {"title": "Castigo ", "season": "1", "chapter": "40", "description": "", "href": "https://clasico.tv/episodes/clarence-1x40/", "sources": ["//sendvid.com/embed/yuc3v4k6"]}, {"title": "Peluquerence", "season": "1", "chapter": "41", "description": "", "href": "https://clasico.tv/episodes/clarence-1x41/", "sources": ["//sendvid.com/embed/yuc3v4k6"]}, {"title": "Amiguito ", "season": "1", "chapter": "42", "description": "", "href": "https://clasico.tv/episodes/clarence-1x42/", "sources": ["//sendvid.com/embed/yuc3v4k6"]}, {"title": "Chalmers Santiago", "season": "1", "chapter": "43", "description": "", "href": "https://clasico.tv/episodes/clarence-1x43/", "sources": ["//sendvid.com/embed/yuc3v4k6"]}, {"title": "Chicos Agotados", "season": "1", "chapter": "44", "description": "", "href": "https://clasico.tv/episodes/clarence-1x44/", "sources": ["//sendvid.com/embed/yuc3v4k6"]}, {"title": "Parque Acu\u00e1tico", "season": "1", "chapter": "45", "description": "", "href": "https://clasico.tv/episodes/clarence-1x45/", "sources": ["//sendvid.com/embed/yuc3v4k6"]}, {"title": "El Regreso de Chad, El Salvaje", "season": "1", "chapter": "46", "description": "", "href": "https://clasico.tv/episodes/clarence-1x46/", "sources": ["//sendvid.com/embed/yuc3v4k6"]}, {"title": "Capit\u00e1n Breehn", "season": "1", "chapter": "47", "description": "", "href": "https://clasico.tv/episodes/clarence-1x47/", "sources": ["//sendvid.com/embed/yuc3v4k6"]}, {"title": "El Problema de la Pizza", "season": "1", "chapter": "48", "description": "", "href": "https://clasico.tv/episodes/clarence-1x48/", "sources": ["//sendvid.com/embed/yuc3v4k6"]}, {"title": "La Separaci\u00f3n", "season": "1", "chapter": "49", "description": "", "href": "https://clasico.tv/episodes/clarence-1x49/", "sources": ["//sendvid.com/embed/yuc3v4k6"]}, {"title": "En Sue\u00f1os ", "season": "1", "chapter": "50", "description": "", "href": "https://clasico.tv/episodes/clarence-1x50/", "sources": ["//sendvid.com/embed/yuc3v4k6"]}, {"title": "Balance ", "season": "1", "chapter": "51", "description": "", "href": "https://clasico.tv/episodes/clarence-1x51/", "sources": ["//sendvid.com/embed/yuc3v4k6"]}, {"title": "Boo Espeluznante", "season": "1", "chapter": "52", "description": "", "href": "https://clasico.tv/episodes/clarence-1x52/", "sources": ["//sendvid.com/embed/yuc3v4k6"]}, {"title": "El Interrogatorio", "season": "2", "chapter": "1", "description": "", "href": "https://clasico.tv/episodes/clarence-2x1/", "sources": ["//sendvid.com/embed/yuc3v4k6"]}, {"title": "El Patio Perdido", "season": "2", "chapter": "2", "description": "", "href": "https://clasico.tv/episodes/clarence-2x2/", "sources": ["//sendvid.com/embed/yuc3v4k6"]}, {"title": "Chico P\u00e1jaro ", "season": "2", "chapter": "3", "description": "", "href": "https://clasico.tv/episodes/clarence-2x3/", "sources": ["//sendvid.com/embed/yuc3v4k6"]}, {"title": "Un Cactus Libre", "season": "2", "chapter": "4", "description": "", "href": "https://clasico.tv/episodes/clarence-2x4/", "sources": ["//sendvid.com/embed/yuc3v4k6"]}, {"title": "Emociones en Vuelo", "season": "2", "chapter": "5", "description": "", "href": "https://clasico.tv/episodes/clarence-2x5/", "sources": ["//sendvid.com/embed/yuc3v4k6"]}, {"title": "Un Escape M\u00e1s All\u00e1 del Cosmos", "season": "2", "chapter": "6", "description": "", "href": "https://clasico.tv/episodes/clarence-2x6/", "sources": ["//sendvid.com/embed/yuc3v4k6"]}, {"title": "Mercado Medieval", "season": "2", "chapter": "7", "description": "", "href": "https://clasico.tv/episodes/clarence-2x7/", "sources": ["//sendvid.com/embed/yuc3v4k6"]}, {"title": "Delitos del Tiempo", "season": "2", "chapter": "8", "description": "", "href": "https://clasico.tv/episodes/clarence-2x8/", "sources": ["//sendvid.com/embed/yuc3v4k6"]}, {"title": "Escuela Sabatina", "season": "2", "chapter": "9", "description": "", "href": "https://clasico.tv/episodes/clarence-2x9/", "sources": ["//sendvid.com/embed/yuc3v4k6"]}, {"title": "Ataque en la Fiesta de la Cuadra", "season": "2", "chapter": "10", "description": "", "href": "https://clasico.tv/episodes/clarence-2x10/", "sources": ["//sendvid.com/embed/yuc3v4k6"]}, {"title": "Excursi\u00f3n ", "season": "2", "chapter": "11", "description": "", "href": "https://clasico.tv/episodes/clarence-2x11/", "sources": ["//sendvid.com/embed/yuc3v4k6"]}, {"title": "Cacer\u00eda de Helados", "season": "2", "chapter": "12", "description": "", "href": "https://clasico.tv/episodes/clarence-2x12/", "sources": ["//sendvid.com/embed/yuc3v4k6"]}, {"title": "Hombre de Empresa", "season": "2", "chapter": "13", "description": "", "href": "https://clasico.tv/episodes/clarence-2x13/", "sources": ["//sendvid.com/embed/yuc3v4k6"]}, {"title": "Hermano Bravuc\u00f3n", "season": "2", "chapter": "14", "description": "", "href": "https://clasico.tv/episodes/clarence-2x14/", "sources": ["//sendvid.com/embed/yuc3v4k6"]}, {"title": "Los Cuentos de Mardrynia", "season": "2", "chapter": "15", "description": "", "href": "https://clasico.tv/episodes/clarence-2x15/", "sources": ["//sendvid.com/embed/yuc3v4k6"]}, {"title": "Clarence Wendle y el misterio de Coogan", "season": "2", "chapter": "16", "description": "", "href": "https://clasico.tv/episodes/clarence-2x16/", "sources": ["//sendvid.com/embed/yuc3v4k6"]}, {"title": "Adelanto ", "season": "2", "chapter": "17", "description": "", "href": "https://clasico.tv/episodes/clarence-2x17/", "sources": ["//sendvid.com/embed/yuc3v4k6"]}, {"title": "Programa de Juegos", "season": "2", "chapter": "18", "description": "", "href": "https://clasico.tv/episodes/clarence-2x18/", "sources": ["//sendvid.com/embed/yuc3v4k6"]}, {"title": "Sumo El Patinador", "season": "2", "chapter": "19", "description": "", "href": "https://clasico.tv/episodes/clarence-2x19/", "sources": ["//sendvid.com/embed/yuc3v4k6"]}, {"title": "La Chica Misteriosa", "season": "2", "chapter": "20", "description": "", "href": "https://clasico.tv/episodes/clarence-2x20/", "sources": ["//sendvid.com/embed/yuc3v4k6"]}, {"title": "La suplente ", "season": "2", "chapter": "21", "description": "", "href": "https://clasico.tv/episodes/clarence-2x21/", "sources": ["//sendvid.com/embed/yuc3v4k6"]}, {"title": "Salon de clases", "season": "2", "chapter": "22", "description": "", "href": "https://clasico.tv/episodes/clarence-2x22/", "sources": ["//sendvid.com/embed/yuc3v4k6"]}, {"title": "El amigo ideal ", "season": "2", "chapter": "23", "description": "", "href": "https://clasico.tv/episodes/clarence-2x23/", "sources": ["//sendvid.com/embed/yuc3v4k6"]}, {"title": "El Secreto de Jeff", "season": "2", "chapter": "24", "description": "", "href": "https://clasico.tv/episodes/clarence-2x24/", "sources": ["//sendvid.com/embed/yuc3v4k6"]}, {"title": "La carrera espacialLa carrera espacial", "season": "2", "chapter": "25", "description": "", "href": "https://clasico.tv/episodes/clarence-2x25/", "sources": ["//sendvid.com/embed/yuc3v4k6"]}, {"title": "La Planta de Papa", "season": "2", "chapter": "26", "description": "", "href": "https://clasico.tv/episodes/clarence-2x26/", "sources": ["//sendvid.com/embed/yuc3v4k6"]}, {"title": "Bucky y el B\u00faho", "season": "2", "chapter": "27", "description": "", "href": "https://clasico.tv/episodes/clarence-2x27/", "sources": ["//sendvid.com/embed/yuc3v4k6"]}, {"title": "La Compostera", "season": "2", "chapter": "28", "description": "", "href": "https://clasico.tv/episodes/clarence-2x28/", "sources": ["//sendvid.com/embed/yuc3v4k6"]}, {"title": "La Dino-aventura de Clarence y Sumo", "season": "2", "chapter": "29", "description": "", "href": "https://clasico.tv/episodes/clarence-2x29/", "sources": ["//sendvid.com/embed/yuc3v4k6"]}, {"title": "El Cumplea\u00f1os", "season": "2", "chapter": "30", "description": "", "href": "https://clasico.tv/episodes/clarence-2x30/", "sources": ["//sendvid.com/embed/yuc3v4k6"]}, {"title": "El \u00c1rbol de la vida", "season": "2", "chapter": "31", "description": "", "href": "https://clasico.tv/episodes/clarence-2x31/", "sources": ["//sendvid.com/embed/yuc3v4k6"]}, {"title": "Captura la bandera", "season": "2", "chapter": "32", "description": "", "href": "https://clasico.tv/episodes/clarence-2x32/", "sources": ["//sendvid.com/embed/yuc3v4k6"]}, {"title": "Cloris ", "season": "2", "chapter": "33", "description": "", "href": "https://clasico.tv/episodes/clarence-2x33/", "sources": ["//sendvid.com/embed/yuc3v4k6"]}, {"title": "Pesca de tres", "season": "2", "chapter": "34", "description": "", "href": "https://clasico.tv/episodes/clarence-2x34/", "sources": ["//sendvid.com/embed/yuc3v4k6"]}, {"title": "La mochila de Belson", "season": "2", "chapter": "35", "description": "", "href": "https://clasico.tv/episodes/clarence-2x35/", "sources": ["//sendvid.com/embed/yuc3v4k6"]}, {"title": "El Motel ", "season": "2", "chapter": "36", "description": "", "href": "https://clasico.tv/episodes/clarence-2x36/", "sources": ["//sendvid.com/embed/yuc3v4k6"]}, {"title": "Feliz Moochividad", "season": "2", "chapter": "37", "description": "", "href": "https://clasico.tv/episodes/clarence-2x37/", "sources": ["//sendvid.com/embed/yuc3v4k6"]}, {"title": "Pizza-h\u00e9roe ", "season": "2", "chapter": "38", "description": "", "href": "https://clasico.tv/episodes/clarence-2x38/", "sources": ["//sendvid.com/embed/yuc3v4k6"]}, {"title": "Sumo va al Oeste", "season": "3", "chapter": "1", "description": "", "href": "https://clasico.tv/episodes/clarence-3x1/", "sources": ["//sendvid.com/embed/yuc3v4k6"]}, {"title": "Epoca de San Valentin", "season": "3", "chapter": "2", "description": "", "href": "https://clasico.tv/episodes/clarence-3x2/", "sources": ["//sendvid.com/embed/yuc3v4k6"]}, {"title": "Clarence Presidente", "season": "3", "chapter": "3", "description": "", "href": "https://clasico.tv/episodes/clarence-3x3/", "sources": ["//sendvid.com/embed/yuc3v4k6"]}, {"title": "El concierto de rock", "season": "3", "chapter": "4", "description": "", "href": "https://clasico.tv/episodes/clarence-3x4/", "sources": ["//sendvid.com/embed/yuc3v4k6"]}, {"title": "El Fantasma Clarence", "season": "3", "chapter": "5", "description": "", "href": "https://clasico.tv/episodes/clarence-3x5/", "sources": ["//sendvid.com/embed/yuc3v4k6"]}, {"title": "Jeffrey Wendle", "season": "3", "chapter": "6", "description": "", "href": "https://clasico.tv/episodes/clarence-3x6/", "sources": ["//sendvid.com/embed/yuc3v4k6"]}, {"title": "Tejones y Bunkers", "season": "3", "chapter": "7", "description": "", "href": "https://clasico.tv/episodes/clarence-3x7/", "sources": ["//sendvid.com/embed/yuc3v4k6"]}, {"title": "Zoquete y McDecerebrado", "season": "3", "chapter": "8", "description": "", "href": "https://clasico.tv/episodes/clarence-3x8/", "sources": ["//sendvid.com/embed/yuc3v4k6"]}, {"title": "Adi\u00f3s, Baker", "season": "3", "chapter": "9", "description": "", "href": "https://clasico.tv/episodes/clarence-3x9/", "sources": ["//sendvid.com/embed/yuc3v4k6"]}, {"title": "Hermanos de Inundacion", "season": "3", "chapter": "10", "description": "", "href": "https://clasico.tv/episodes/clarence-3x10/", "sources": ["//sendvid.com/embed/yuc3v4k6"]}, {"title": "Las piscinas son para el verano sub espa\u00f1ol", "season": "3", "chapter": "11", "description": "", "href": "https://clasico.tv/episodes/clarence-3x11/", "sources": ["//sendvid.com/embed/yuc3v4k6"]}, {"title": "El gran partido sub espa\u00f1ol", "season": "3", "chapter": "12", "description": "", "href": "https://clasico.tv/episodes/clarence-3x12/", "sources": ["//sendvid.com/embed/yuc3v4k6"]}, {"title": "Los ni\u00f1os de la caja maldita", "season": "3", "chapter": "13", "description": "", "href": "https://clasico.tv/episodes/clarence-3x13/", "sources": ["//sendvid.com/embed/yuc3v4k6"]}, {"title": "Mami karate sub espa\u00f1ol", "season": "3", "chapter": "14", "description": "", "href": "https://clasico.tv/episodes/clarence-3x14/", "sources": ["//sendvid.com/embed/yuc3v4k6"]}, {"title": "Clarence adora a Shoopy", "season": "3", "chapter": "15", "description": "", "href": "https://clasico.tv/episodes/clarence-3x15/", "sources": ["//sendvid.com/embed/yuc3v4k6"]}, {"title": "Radio p\u00fablica sub espa\u00f1ol", "season": "3", "chapter": "16", "description": "", "href": "https://clasico.tv/episodes/clarence-3x16/", "sources": ["//sendvid.com/embed/yuc3v4k6"]}, {"title": "Chad y el marat\u00f3n", "season": "3", "chapter": "17", "description": "", "href": "https://clasico.tv/episodes/clarence-3x17/", "sources": ["//sendvid.com/embed/yuc3v4k6"]}, {"title": "Oficial Moody", "season": "3", "chapter": "18", "description": "", "href": "https://clasico.tv/episodes/clarence-3x18/", "sources": ["//sendvid.com/embed/yuc3v4k6"]}, {"title": "Gilben es diferente", "season": "3", "chapter": "19", "description": "", "href": "https://clasico.tv/episodes/clarence-3x19/", "sources": ["//sendvid.com/embed/yuc3v4k6"]}, {"title": "Clarence genial", "season": "3", "chapter": "20", "description": "", "href": "https://clasico.tv/episodes/clarence-3x20/", "sources": ["//sendvid.com/embed/yuc3v4k6"]}, {"title": "Espera en el coche sub espa\u00f1ol", "season": "3", "chapter": "21", "description": "", "href": "https://clasico.tv/episodes/clarence-3x21/", "sources": ["//sendvid.com/embed/yuc3v4k6"]}, {"title": "El gato perdido", "season": "3", "chapter": "22", "description": "", "href": "https://clasico.tv/episodes/clarence-3x22/", "sources": ["//sendvid.com/embed/yuc3v4k6"]}, {"title": "Grandes problemas en la peque\u00f1a Aberdale sub espa\u00f1ol", "season": "3", "chapter": "23", "description": "", "href": "https://clasico.tv/episodes/clarence-3x23/", "sources": ["//sendvid.com/embed/yuc3v4k6"]}, {"title": "El d\u00eda de los retos", "season": "3", "chapter": "24", "description": "", "href": "https://clasico.tv/episodes/clarence-3x24/", "sources": ["//sendvid.com/embed/yuc3v4k6"]}, {"title": "Intercambio ", "season": "3", "chapter": "25", "description": "", "href": "https://clasico.tv/episodes/clarence-3x25/", "sources": ["//sendvid.com/embed/yuc3v4k6"]}, {"title": "La venganza del equilibrio", "season": "3", "chapter": "26", "description": "", "href": "https://clasico.tv/episodes/clarence-3x26/", "sources": ["//sendvid.com/embed/yuc3v4k6"]}, {"title": "El dia de accion de Chad sub espa\u00f1ol", "season": "3", "chapter": "27", "description": "", "href": "https://clasico.tv/episodes/clarence-3x27/", "sources": ["//sendvid.com/embed/yuc3v4k6"]}, {"title": "Una mente Sumo-villosa", "season": "3", "chapter": "28", "description": "", "href": "https://clasico.tv/episodes/clarence-3x28/", "sources": ["//sendvid.com/embed/yuc3v4k6"]}, {"title": "D\u00eda animal ", "season": "3", "chapter": "29", "description": "", "href": "https://clasico.tv/episodes/clarence-3x29/", "sources": ["//sendvid.com/embed/yuc3v4k6"]}, {"title": "El t\u00fanel ", "season": "3", "chapter": "30", "description": "", "href": "https://clasico.tv/episodes/clarence-3x30/", "sources": ["//sendvid.com/embed/yuc3v4k6"]}, {"title": "Concurso de talentos", "season": "3", "chapter": "31", "description": "", "href": "https://clasico.tv/episodes/clarence-3x31/", "sources": ["//sendvid.com/embed/yuc3v4k6"]}, {"title": "Auto a control remoto", "season": "3", "chapter": "32", "description": "", "href": "https://clasico.tv/episodes/clarence-3x32/", "sources": ["//sendvid.com/embed/yuc3v4k6"]}, {"title": "Clarence, el rey de los perros", "season": "3", "chapter": "33", "description": "", "href": "https://clasico.tv/episodes/clarence-3x33/", "sources": ["//sendvid.com/embed/yuc3v4k6"]}, {"title": "Trampol\u00edn ", "season": "3", "chapter": "34", "description": "", "href": "https://clasico.tv/episodes/clarence-3x34/", "sources": ["//sendvid.com/embed/yuc3v4k6"]}, {"title": "Clarence la Pelicula", "season": "3", "chapter": "35", "description": "", "href": "https://clasico.tv/episodes/clarence-3x35/", "sources": ["//sendvid.com/embed/yuc3v4k6"]}, {"title": "Belson tiene novia", "season": "3", "chapter": "36", "description": "", "href": "https://clasico.tv/episodes/clarence-3x36/", "sources": ["//sendvid.com/embed/yuc3v4k6"]}, {"title": "Cerebro de TV", "season": "3", "chapter": "37", "description": "", "href": "https://clasico.tv/episodes/clarence-3x37/", "sources": ["//sendvid.com/embed/yuc3v4k6"]}, {"title": "Clases de etiqueta para Clarence", "season": "3", "chapter": "38", "description": "", "href": "https://clasico.tv/episodes/clarence-3x38/", "sources": ["//sendvid.com/embed/yuc3v4k6"]}, {"title": "aun no se estrena", "season": "3", "chapter": "39", "description": "", "href": "https://clasico.tv/episodes/clarence-3x39/", "sources": ["//sendvid.com/embed/yuc3v4k6"]}, {"title": "En cualquier lugar pero con Sumo", "season": "3", "chapter": "40", "description": "", "href": "https://clasico.tv/episodes/clarence-3x40/", "sources": ["//sendvid.com/embed/yuc3v4k6"]}, {"title": "Cortos \u2013 1 al 14", "season": "3", "chapter": "41", "description": "", "href": "https://clasico.tv/episodes/clarence-3x41/", "sources": ["//sendvid.com/embed/yuc3v4k6"]}]