[{"title": "El Casco Fenomenal", "season": "1", "chapter": "1", "description": "", "href": "https://clasico.tv/episodes/irmao-do-jorel-1x1/", "sources": ["//sendvid.com/embed/yuc3v4k6"]}, {"title": "El Sube y Baja de la Revoluci\u00f3n", "season": "1", "chapter": "2", "description": "", "href": "https://clasico.tv/episodes/irmao-do-jorel-1x2/", "sources": ["//sendvid.com/embed/yuc3v4k6"]}, {"title": "El Club de la Lucha Libre", "season": "1", "chapter": "3", "description": "", "href": "https://clasico.tv/episodes/irmao-do-jorel-1x3/", "sources": ["//sendvid.com/embed/yuc3v4k6"]}, {"title": "No Les Temas a Tus Miedos", "season": "1", "chapter": "4", "description": "", "href": "https://clasico.tv/episodes/irmao-do-jorel-1x4/", "sources": ["//sendvid.com/embed/yuc3v4k6"]}, {"title": "El noticiero del Jard\u00edn", "season": "1", "chapter": "5", "description": "", "href": "https://clasico.tv/episodes/irmao-do-jorel-1x5/", "sources": ["//sendvid.com/embed/yuc3v4k6"]}, {"title": "El misterio de Las notitas super secretas", "season": "1", "chapter": "6", "description": "", "href": "https://clasico.tv/episodes/irmao-do-jorel-1x6/", "sources": ["//sendvid.com/embed/yuc3v4k6"]}, {"title": "La peligrosa lambada brutal", "season": "1", "chapter": "7", "description": "", "href": "https://clasico.tv/episodes/irmao-do-jorel-1x7/", "sources": ["//sendvid.com/embed/yuc3v4k6"]}, {"title": "La Historia Sin Comienzo, Ni Medio, Ni Fin", "season": "1", "chapter": "8", "description": "", "href": "https://clasico.tv/episodes/irmao-do-jorel-1x8/", "sources": ["//sendvid.com/embed/yuc3v4k6"]}, {"title": "El Rostro de la Expresividad M\u00e1xima", "season": "1", "chapter": "9", "description": "", "href": "https://clasico.tv/episodes/irmao-do-jorel-1x9/", "sources": ["//sendvid.com/embed/yuc3v4k6"]}, {"title": "El Ataque de los Piojos Mutantes", "season": "1", "chapter": "10", "description": "", "href": "https://clasico.tv/episodes/irmao-do-jorel-1x10/", "sources": ["//sendvid.com/embed/yuc3v4k6"]}, {"title": "Naturaleza Totalmente Salvaje", "season": "1", "chapter": "11", "description": "", "href": "https://clasico.tv/episodes/irmao-do-jorel-1x11/", "sources": ["//sendvid.com/embed/yuc3v4k6"]}, {"title": "La Implacable Jornada Matinal", "season": "1", "chapter": "12", "description": "", "href": "https://clasico.tv/episodes/irmao-do-jorel-1x12/", "sources": ["//sendvid.com/embed/yuc3v4k6"]}, {"title": "La Aterradora Vida de Los Adultos", "season": "1", "chapter": "13", "description": "", "href": "https://clasico.tv/episodes/irmao-do-jorel-1x13/", "sources": ["//sendvid.com/embed/yuc3v4k6"]}, {"title": "El boligrafo de 250 colores", "season": "1", "chapter": "14", "description": "", "href": "https://clasico.tv/episodes/irmao-do-jorel-1x14/", "sources": ["//sendvid.com/embed/yuc3v4k6"]}, {"title": "Unete a la moda", "season": "1", "chapter": "15", "description": "", "href": "https://clasico.tv/episodes/irmao-do-jorel-1x15/", "sources": ["//sendvid.com/embed/yuc3v4k6"]}, {"title": "Profesion: payaso", "season": "1", "chapter": "16", "description": "", "href": "https://clasico.tv/episodes/irmao-do-jorel-1x16/", "sources": ["//sendvid.com/embed/yuc3v4k6"]}, {"title": "Una odisea en el espacio recreativo", "season": "1", "chapter": "17", "description": "", "href": "https://clasico.tv/episodes/irmao-do-jorel-1x17/", "sources": ["//sendvid.com/embed/yuc3v4k6"]}, {"title": "Los cazadores del cromo perdido", "season": "1", "chapter": "18", "description": "", "href": "https://clasico.tv/episodes/irmao-do-jorel-1x18/", "sources": ["//sendvid.com/embed/yuc3v4k6"]}, {"title": "Juegos mortales", "season": "1", "chapter": "19", "description": "", "href": "https://clasico.tv/episodes/irmao-do-jorel-1x19/", "sources": ["//sendvid.com/embed/yuc3v4k6"]}, {"title": "La isla loca", "season": "1", "chapter": "20", "description": "", "href": "https://clasico.tv/episodes/irmao-do-jorel-1x20/", "sources": ["//sendvid.com/embed/yuc3v4k6"]}, {"title": "Los increibles viejo adolescentes", "season": "1", "chapter": "21", "description": "", "href": "https://clasico.tv/episodes/irmao-do-jorel-1x21/", "sources": ["//sendvid.com/embed/yuc3v4k6"]}, {"title": "La leyenda de la mujer de algodon", "season": "1", "chapter": "22", "description": "", "href": "https://clasico.tv/episodes/irmao-do-jorel-1x22/", "sources": ["//sendvid.com/embed/yuc3v4k6"]}, {"title": "Familia a la deriva", "season": "1", "chapter": "23", "description": "", "href": "https://clasico.tv/episodes/irmao-do-jorel-1x23/", "sources": ["//sendvid.com/embed/yuc3v4k6"]}, {"title": "El peque\u00f1o maestro de gi gitsu", "season": "1", "chapter": "24", "description": "", "href": "https://clasico.tv/episodes/irmao-do-jorel-1x24/", "sources": ["//sendvid.com/embed/yuc3v4k6"]}, {"title": "Furia y poder sobre ruedas", "season": "1", "chapter": "25", "description": "", "href": "https://clasico.tv/episodes/irmao-do-jorel-1x25/", "sources": ["//sendvid.com/embed/yuc3v4k6"]}, {"title": "Mi segundo amor", "season": "1", "chapter": "26", "description": "", "href": "https://clasico.tv/episodes/irmao-do-jorel-1x26/", "sources": ["//sendvid.com/embed/yuc3v4k6"]}, {"title": "Carlos felino consejero amoroso", "season": "2", "chapter": "1", "description": "", "href": "https://clasico.tv/episodes/irmao-do-jorel-2x1/", "sources": ["//sendvid.com/embed/yuc3v4k6"]}, {"title": "Fluffy el delfin asesino", "season": "2", "chapter": "2", "description": "", "href": "https://clasico.tv/episodes/irmao-do-jorel-2x2/", "sources": ["//sendvid.com/embed/yuc3v4k6"]}, {"title": "Centro shosters", "season": "2", "chapter": "3", "description": "", "href": "https://clasico.tv/episodes/irmao-do-jorel-2x3/", "sources": ["//sendvid.com/embed/yuc3v4k6"]}, {"title": "Penitencia o penitencia", "season": "2", "chapter": "4", "description": "", "href": "https://clasico.tv/episodes/irmao-do-jorel-2x4/", "sources": ["//sendvid.com/embed/yuc3v4k6"]}, {"title": "A traves del armario", "season": "2", "chapter": "5", "description": "", "href": "https://clasico.tv/episodes/irmao-do-jorel-2x5/", "sources": ["//sendvid.com/embed/yuc3v4k6"]}, {"title": "Excursi\u00f3n alucinante desenfrenada", "season": "2", "chapter": "6", "description": "", "href": "https://clasico.tv/episodes/irmao-do-jorel-2x6/", "sources": ["//sendvid.com/embed/yuc3v4k6"]}, {"title": "La fant\u00e1stica f\u00e1brica de soda", "season": "2", "chapter": "7", "description": "", "href": "https://clasico.tv/episodes/irmao-do-jorel-2x7/", "sources": ["//sendvid.com/embed/yuc3v4k6"]}, {"title": "Campamento brutal", "season": "2", "chapter": "8", "description": "", "href": "https://clasico.tv/episodes/irmao-do-jorel-2x8/", "sources": ["//sendvid.com/embed/yuc3v4k6"]}, {"title": "Entonces es navidad", "season": "2", "chapter": "9", "description": "", "href": "https://clasico.tv/episodes/irmao-do-jorel-2x9/", "sources": ["//sendvid.com/embed/yuc3v4k6"]}, {"title": "La vida secreta de los bellecitos", "season": "2", "chapter": "10", "description": "", "href": "https://clasico.tv/episodes/irmao-do-jorel-2x10/", "sources": ["//sendvid.com/embed/yuc3v4k6"]}, {"title": "M.C. Juju", "season": "2", "chapter": "11", "description": "", "href": "https://clasico.tv/episodes/irmao-do-jorel-2x11/", "sources": ["//sendvid.com/embed/yuc3v4k6"]}, {"title": "Juergas de sabado en la tarde", "season": "2", "chapter": "12", "description": "", "href": "https://clasico.tv/episodes/irmao-do-jorel-2x12/", "sources": ["//sendvid.com/embed/yuc3v4k6"]}, {"title": "Exito interplanetario", "season": "2", "chapter": "13", "description": "", "href": "https://clasico.tv/episodes/irmao-do-jorel-2x13/", "sources": ["//sendvid.com/embed/yuc3v4k6"]}, {"title": "Maquinito el robot amigo", "season": "2", "chapter": "14", "description": "", "href": "https://clasico.tv/episodes/irmao-do-jorel-2x14/", "sources": ["//sendvid.com/embed/yuc3v4k6"]}, {"title": "Sedosa crema doble crema", "season": "2", "chapter": "15", "description": "", "href": "https://clasico.tv/episodes/irmao-do-jorel-2x15/", "sources": ["//sendvid.com/embed/yuc3v4k6"]}, {"title": "Shostners Burguer", "season": "2", "chapter": "16", "description": "", "href": "https://clasico.tv/episodes/irmao-do-jorel-2x16/", "sources": ["//sendvid.com/embed/yuc3v4k6"]}, {"title": "El hermano de nico", "season": "2", "chapter": "17", "description": "", "href": "https://clasico.tv/episodes/irmao-do-jorel-2x17/", "sources": ["//sendvid.com/embed/yuc3v4k6"]}, {"title": "Perdido en el cine", "season": "2", "chapter": "18", "description": "", "href": "https://clasico.tv/episodes/irmao-do-jorel-2x18/", "sources": ["//sendvid.com/embed/yuc3v4k6"]}, {"title": "Parque de diversiones Adelino", "season": "2", "chapter": "19", "description": "", "href": "https://clasico.tv/episodes/irmao-do-jorel-2x19/", "sources": ["//sendvid.com/embed/yuc3v4k6"]}, {"title": "De regreso al futuro del pasado", "season": "2", "chapter": "20", "description": "", "href": "https://clasico.tv/episodes/irmao-do-jorel-2x20/", "sources": ["//sendvid.com/embed/yuc3v4k6"]}, {"title": "Recreo brutal", "season": "2", "chapter": "21", "description": "", "href": "https://clasico.tv/episodes/irmao-do-jorel-2x21/", "sources": ["//sendvid.com/embed/yuc3v4k6"]}, {"title": "Enemigo imaginario", "season": "2", "chapter": "22", "description": "", "href": "https://clasico.tv/episodes/irmao-do-jorel-2x22/", "sources": ["//sendvid.com/embed/yuc3v4k6"]}, {"title": "En busca de la libertad", "season": "2", "chapter": "23", "description": "", "href": "https://clasico.tv/episodes/irmao-do-jorel-2x23/", "sources": ["//sendvid.com/embed/yuc3v4k6"]}, {"title": "Elefante de porcelana", "season": "2", "chapter": "24", "description": "", "href": "https://clasico.tv/episodes/irmao-do-jorel-2x24/", "sources": ["//sendvid.com/embed/yuc3v4k6"]}, {"title": "Durmiendo despierto", "season": "2", "chapter": "25", "description": "", "href": "https://clasico.tv/episodes/irmao-do-jorel-2x25/", "sources": ["//sendvid.com/embed/yuc3v4k6"]}, {"title": "Expulsado especial", "season": "2", "chapter": "26", "description": "", "href": "https://clasico.tv/episodes/irmao-do-jorel-2x26/", "sources": ["//sendvid.com/embed/yuc3v4k6"]}, {"title": "Un huerto genial", "season": "3", "chapter": "1", "description": "", "href": "https://clasico.tv/episodes/irmao-do-jorel-3x1/", "sources": ["//sendvid.com/embed/yuc3v4k6"]}, {"title": "El hermanito de jorel", "season": "3", "chapter": "2", "description": "", "href": "https://clasico.tv/episodes/irmao-do-jorel-3x2/", "sources": ["//sendvid.com/embed/yuc3v4k6"]}, {"title": "Amo de casa", "season": "3", "chapter": "3", "description": "", "href": "https://clasico.tv/episodes/irmao-do-jorel-3x3/", "sources": ["//sendvid.com/embed/yuc3v4k6"]}, {"title": "Edd show", "season": "3", "chapter": "4", "description": "", "href": "https://clasico.tv/episodes/irmao-do-jorel-3x4/", "sources": ["//sendvid.com/embed/yuc3v4k6"]}, {"title": "El cometa ideal", "season": "3", "chapter": "5", "description": "", "href": "https://clasico.tv/episodes/irmao-do-jorel-3x5/", "sources": ["//sendvid.com/embed/yuc3v4k6"]}, {"title": "El mas loco de la escuela", "season": "3", "chapter": "6", "description": "", "href": "https://clasico.tv/episodes/irmao-do-jorel-3x6/", "sources": ["//sendvid.com/embed/yuc3v4k6"]}, {"title": "Abuela llevame a la escuela", "season": "3", "chapter": "7", "description": "", "href": "https://clasico.tv/episodes/irmao-do-jorel-3x7/", "sources": ["//sendvid.com/embed/yuc3v4k6"]}, {"title": "El hipo eterno", "season": "3", "chapter": "8", "description": "", "href": "https://clasico.tv/episodes/irmao-do-jorel-3x8/", "sources": ["//sendvid.com/embed/yuc3v4k6"]}]