[{"title": "Piloto", "season": 1, "chapter": 1, "description": "", "sources": ["https://sendvid.com/embed/u35g6lcc"]}, {"title": "Quiero m\u00e1s p\u00fablico", "season": 1, "chapter": 2, "description": "", "sources": ["https://sendvid.com/embed/gww4gfjz"]}, {"title": "Sue\u00f1o con bailar", "season": 1, "chapter": 3, "description": "", "sources": ["https://sendvid.com/embed/rj3jqudf"]}, {"title": "Me gusta Jake", "season": 1, "chapter": 4, "description": "", "sources": ["https://sendvid.com/embed/s4s7usff"]}, {"title": "Me quiero quedar con Spencer", "season": 1, "chapter": 5, "description": "", "sources": ["https://sendvid.com/embed/xzer2kip"]}, {"title": "iNevel", "season": 1, "chapter": 6, "description": "", "sources": ["https://sendvid.com/embed/8vqwusp5"]}, {"title": "Gritando en Halloween", "season": 1, "chapter": 7, "description": "", "sources": ["https://sendvid.com/embed/q9i48ioc"]}, {"title": "Espiando a la maestra malvada", "season": 1, "chapter": 8, "description": "", "sources": ["https://sendvid.com/embed/uwidzd83"]}, {"title": "Quiero salir con Freddie", "season": 1, "chapter": 9, "description": "", "sources": ["https://sendvid.com/embed/jhrnf25p"]}, {"title": "Quiero romper un r\u00e9cord mundial", "season": 1, "chapter": 10, "description": "", "sources": ["https://sendvid.com/embed/gyqxtkru"]}, {"title": "Pla\u00f1ir\u00e9 el d\u00eda", "season": 1, "chapter": 11, "description": "", "sources": ["https://sendvid.com/embed/ffb6zep2"]}, {"title": "Prometo guardar el secreto", "season": 1, "chapter": 12, "description": "", "sources": ["https://sendvid.com/embed/fr4prd1u"]}, {"title": "La fan m\u00e1s grande", "season": 1, "chapter": 13, "description": "", "sources": ["https://sendvid.com/embed/7qodwbek"]}, {"title": "Amo el arte", "season": 1, "chapter": 14, "description": "", "sources": ["https://sendvid.com/embed/as07dpyg"]}, {"title": "Odio al novio de Sam", "season": 1, "chapter": 15, "description": "", "sources": ["https://sendvid.com/embed/g6b1omei"]}, {"title": "Cazando pollos", "season": 1, "chapter": 16, "description": "", "sources": ["https://sendvid.com/embed/kywsvdx7"]}, {"title": "No quiero pelear", "season": 1, "chapter": 17, "description": "", "sources": ["https://sendvid.com/embed/ku57ui9a"]}, {"title": "Anunciando Techfoots", "season": 1, "chapter": 18, "description": "", "sources": ["https://sendvid.com/embed/jierlpjr"]}, {"title": "Todos a detenci\u00f3n", "season": 1, "chapter": 19, "description": "", "sources": ["https://sendvid.com/embed/g4877zpb"]}, {"title": "La emboscada", "season": 1, "chapter": 20, "description": "", "sources": ["https://sendvid.com/embed/1zs8m7ei"]}, {"title": "El cambio de escuela", "season": 1, "chapter": 21, "description": "", "sources": ["https://sendvid.com/embed/2aubdlo5"]}, {"title": "Esgrima", "season": 1, "chapter": 22, "description": "", "sources": ["https://sendvid.com/embed/6jg4mkyt"]}, {"title": "iCarly salva la televisi\u00f3n", "season": 1, "chapter": 23, "description": "", "sources": ["https://sendvid.com/embed/0pwpyb4s"]}, {"title": "Gan\u00e9 una cita", "season": 1, "chapter": 24, "description": "", "sources": ["https://sendvid.com/embed/m87zy20e"]}, {"title": "Mi maestra est\u00e1 enferma de amor", "season": 1, "chapter": 25, "description": "", "sources": ["https://sendvid.com/embed/4dywna39"]}, {"title": "Yo lo vi primero", "season": 2, "chapter": 1, "description": "", "sources": ["https://sendvid.com/embed/unzr4ezk"]}, {"title": "La intervenci\u00f3n", "season": 2, "chapter": 2, "description": "", "sources": ["https://sendvid.com/embed/k14bjkdn"]}, {"title": "La deuda", "season": 2, "chapter": 3, "description": "", "sources": ["https://sendvid.com/embed/brzxknjl"]}, {"title": "Lastimamos a Lewbert", "season": 2, "chapter": 4, "description": "", "sources": ["https://sendvid.com/embed/9p104srd"]}, {"title": "iCarly en Jap\u00f3n Parte I,II y III", "season": 2, "chapter": 5, "description": "", "sources": ["https://sendvid.com/embed/hwyjxdrv"]}, {"title": "Locos por las tartas", "season": 2, "chapter": 6, "description": "", "sources": ["https://sendvid.com/embed/f6g1z987"]}, {"title": "La Navidad", "season": 2, "chapter": 7, "description": "", "sources": ["https://sendvid.com/embed/56gooq8h"]}, {"title": "El primer beso", "season": 2, "chapter": 8, "description": "", "sources": ["https://sendvid.com/embed/u8276iit"]}, {"title": "Regalo un auto", "season": 2, "chapter": 9, "description": "", "sources": ["https://sendvid.com/embed/wnd0en36"]}, {"title": "Afect\u00e9 la votaci\u00f3n", "season": 2, "chapter": 10, "description": "", "sources": ["https://sendvid.com/embed/3515ui96"]}, {"title": "Fred est\u00e1 muerto", "season": 2, "chapter": 11, "description": "", "sources": ["https://sendvid.com/embed/1p9zchbi"]}, {"title": "Mmm... Me parezco", "season": 2, "chapter": 12, "description": "", "sources": ["https://sendvid.com/embed/gbduikxv"]}, {"title": "Devu\u00e9lveme mi Website", "season": 2, "chapter": 13, "description": "", "sources": ["https://sendvid.com/embed/w7cmk7ff"]}, {"title": "Haciendo femenina a Sam", "season": 2, "chapter": 14, "description": "", "sources": ["https://sendvid.com/embed/xyi2otsa"]}, {"title": "Nos hacemos nucleares", "season": 2, "chapter": 15, "description": "", "sources": ["https://sendvid.com/embed/b5slco0x"]}, {"title": "Salgo con un chico malo Parte I y II", "season": 2, "chapter": 16, "description": "", "sources": ["https://sendvid.com/embed/csmunqf9"]}, {"title": "El reencuentro con Missy", "season": 2, "chapter": 17, "description": "", "sources": ["https://sendvid.com/embed/ceg1a4pu"]}, {"title": "Plagio", "season": 2, "chapter": 18, "description": "", "sources": ["https://sendvid.com/embed/4uv8vhii"]}, {"title": "Debo tener el casillero 239", "season": 2, "chapter": 19, "description": "", "sources": ["https://sendvid.com/embed/1rga7f04"]}, {"title": "Gemelas", "season": 2, "chapter": 20, "description": "", "sources": ["https://sendvid.com/embed/zx1r5mcb"]}, {"title": "Yo peleo con Shelby Marx", "season": 2, "chapter": 21, "description": "", "sources": ["https://sendvid.com/embed/wf9q3j09"]}, {"title": "Creo que se dieron un beso", "season": 3, "chapter": 1, "description": "", "sources": ["https://sendvid.com/embed/l9g9rhoh"]}, {"title": "A cocinar", "season": 3, "chapter": 2, "description": "", "sources": ["https://sendvid.com/embed/63ixyrac"]}, {"title": "Cita rel\u00e1mpago", "season": 3, "chapter": 3, "description": "", "sources": ["https://sendvid.com/embed/eyqymicl"]}, {"title": "Los premios iCarly", "season": 3, "chapter": 4, "description": "", "sources": ["https://sendvid.com/embed/yje7pmzk"]}, {"title": "Directores", "season": 3, "chapter": 5, "description": "", "sources": ["https://sendvid.com/embed/txrc9g7n"]}, {"title": "El amor perdido de Lewbert", "season": 3, "chapter": 6, "description": "", "sources": ["https://sendvid.com/embed/y8aj21ys"]}, {"title": "El nuevo hogar", "season": 3, "chapter": 7, "description": "", "sources": ["https://sendvid.com/embed/w701eo2g"]}, {"title": "Renuncio a iCarly Parte I y II", "season": 3, "chapter": 8, "description": "", "sources": ["https://sendvid.com/embed/0yuyyjv9"]}, {"title": "Te salv\u00e9 la vida", "season": 3, "chapter": 9, "description": "", "sources": ["https://sendvid.com/embed/whyo3wb0"]}, {"title": "Yo fui chica de concurso de belleza", "season": 3, "chapter": 10, "description": "", "sources": ["https://sendvid.com/embed/sq19r0w8"]}, {"title": "La furia de Gibby", "season": 3, "chapter": 11, "description": "", "sources": ["https://sendvid.com/embed/ov7cxwb0"]}, {"title": "El espacio exterior", "season": 3, "chapter": 12, "description": "", "sources": ["https://sendvid.com/embed/cq9nwu56"]}, {"title": "Creamos una estrella del pop", "season": 3, "chapter": 13, "description": "", "sources": ["https://sendvid.com/embed/4uorul7e"]}, {"title": "Ay, me equivoqu\u00e9", "season": 3, "chapter": 14, "description": "", "sources": ["https://sendvid.com/embed/dzech4u6"]}, {"title": "No cancelar\u00e9 el show", "season": 3, "chapter": 15, "description": "", "sources": ["https://sendvid.com/embed/82dajo78"]}, {"title": "Yo s\u00ed creo en pie grande", "season": 3, "chapter": 16, "description": "", "sources": ["https://sendvid.com/embed/40d08oob"]}, {"title": "La psic\u00f3pata Parte I y II", "season": 3, "chapter": 17, "description": "", "sources": ["https://sendvid.com/embed/oyupe1yp"]}, {"title": "Yo venc\u00ed al calor", "season": 3, "chapter": 18, "description": "", "sources": ["https://sendvid.com/embed/gmi6lwwu"]}, {"title": "Una habitaci\u00f3n ardiente", "season": 4, "chapter": 1, "description": "", "sources": ["https://sendvid.com/embed/1hlz6z68"]}, {"title": "La mam\u00e1 de Sam", "season": 4, "chapter": 2, "description": "", "sources": ["https://sendvid.com/embed/xj3ayrch"]}, {"title": "Me vuelvo bromista", "season": 4, "chapter": 3, "description": "", "sources": ["https://sendvid.com/embed/w43d0p20"]}, {"title": "Vendiendo camisetas de a centavo", "season": 4, "chapter": 4, "description": "", "sources": ["https://sendvid.com/embed/7fwm88st"]}, {"title": "Acepto", "season": 4, "chapter": 5, "description": "", "sources": ["https://sendvid.com/embed/9jefk35f"]}, {"title": "La guerra de los fans Parte I y II", "season": 4, "chapter": 6, "description": "", "sources": ["https://sendvid.com/embed/y7c7q43m"]}, {"title": "Contrat\u00e9 a un tonto", "season": 4, "chapter": 7, "description": "", "sources": ["https://sendvid.com/embed/2zc198s1"]}, {"title": "Pobre Nevel", "season": 4, "chapter": 8, "description": "", "sources": ["https://sendvid.com/embed/fn2xdee9"]}, {"title": "\u00a1Ay, por Dios!", "season": 4, "chapter": 9, "description": "", "sources": ["https://sendvid.com/embed/u4mlz9b0"]}, {"title": "Fiesta con Victorious Parte I, II y III", "season": 4, "chapter": 10, "description": "", "sources": ["https://sendvid.com/embed/ae6anub6"]}, {"title": "Perd\u00ed la cabeza", "season": 5, "chapter": 1, "description": "", "sources": ["https://sendvid.com/embed/sumavonn"]}, {"title": "La cita de Sam y Freddie", "season": 5, "chapter": 2, "description": "", "sources": ["https://sendvid.com/embed/mntlqx16"]}, {"title": "Ellos deben terminar", "season": 5, "chapter": 3, "description": "", "sources": ["https://sendvid.com/embed/26zbnjxa"]}, {"title": "Te amo", "season": 5, "chapter": 4, "description": "", "sources": ["https://sendvid.com/embed/clzxpccg"]}, {"title": "Coeficiente intelectual", "season": 5, "chapter": 5, "description": "", "sources": ["https://sendvid.com/embed/izhb8ypx"]}, {"title": "Una Noche con iCarly", "season": 5, "chapter": 6, "description": "", "sources": ["https://sendvid.com/embed/qh429z9o"]}, {"title": "M\u00e1s psic\u00f3pata que nunca Parte I y II", "season": 5, "chapter": 7, "description": "", "sources": ["https://sendvid.com/embed/71j3cihf"]}, {"title": "Globos oculares", "season": 5, "chapter": 8, "description": "", "sources": ["https://sendvid.com/embed/2ghk5ryt"]}, {"title": "Conociendo a la Primera Dama", "season": 5, "chapter": 9, "description": "", "sources": ["https://sendvid.com/embed/c11f17oe"]}, {"title": "Loca por los grasitos", "season": 5, "chapter": 10, "description": "", "sources": ["https://sendvid.com/embed/jvf2ya9e"]}, {"title": "D\u00eda de los Inocentes", "season": 6, "chapter": 1, "description": "", "sources": ["https://sendvid.com/embed/b7vlgrom"]}, {"title": "Conociendo a One Direction", "season": 6, "chapter": 2, "description": "", "sources": ["https://sendvid.com/embed/1a2ozm7a"]}, {"title": "Abr\u00ed un restaurante", "season": 6, "chapter": 3, "description": "", "sources": ["https://sendvid.com/embed/0wpzel7i"]}, {"title": "MedioWeen", "season": 6, "chapter": 4, "description": "", "sources": ["https://sendvid.com/embed/nrr14slt"]}, {"title": "Trabajando en PeraStore", "season": 6, "chapter": 5, "description": "", "sources": ["https://sendvid.com/embed/w52whqzg"]}, {"title": "El Phaser", "season": 6, "chapter": 6, "description": "", "sources": ["https://sendvid.com/embed/xj31a2kt"]}, {"title": "Sorprendiendo a Am\u00e9rica Parte I y II", "season": 6, "chapter": 7, "description": "", "sources": ["https://sendvid.com/embed/27gw823a"]}, {"title": "Estoy vetado", "season": 6, "chapter": 8, "description": "", "sources": ["https://sendvid.com/embed/t0gw2k9l"]}, {"title": "Amigos para Spencer", "season": 6, "chapter": 9, "description": "", "sources": ["https://sendvid.com/embed/u8swcuev"]}, {"title": "El rescate de Carly", "season": 6, "chapter": 10, "description": "", "sources": ["https://sendvid.com/embed/3s5nyki6"]}, {"title": "Perdiendo la cabeza en Las Vegas", "season": 6, "chapter": 11, "description": "", "sources": ["https://sendvid.com/embed/l90ibfya"]}, {"title": "La captura del ladr\u00f3n", "season": 6, "chapter": 12, "description": "", "sources": ["https://sendvid.com/embed/titbphvn"]}, {"title": "El adi\u00f3s Parte I y II", "season": 6, "chapter": 13, "description": "", "sources": ["https://sendvid.com/embed/e338m4qa"]}]