[{"title": "Ahora lo Pitufeas y ahora no / La Gran Sequ\u00eda", "season": 1, "chapter": 1, "description": "", "sources": ["https://ok.ru/videoembed/1825527695945"]}, {"title": "El amigo m\u00e1s pitufo", "season": 1, "chapter": 2, "description": "", "sources": ["https://ok.ru/videoembed/1825529137737"]}, {"title": "El Astropitufo", "season": 1, "chapter": 3, "description": "", "sources": ["https://ok.ru/videoembed/1825528023625"]}, {"title": "El Bromista burlado", "season": 1, "chapter": 4, "description": "", "sources": ["https://ok.ru/videoembed/1825529072201"]}, {"title": "El cent\u00e9simo Pitufo", "season": 1, "chapter": 5, "description": "", "sources": ["https://ok.ru/videoembed/1825528351305"]}, {"title": "El huevo m\u00e1gico", "season": 1, "chapter": 6, "description": "", "sources": ["https://ok.ru/videoembed/1825529268809"]}, {"title": "El Mal Genio", "season": 1, "chapter": 7, "description": "", "sources": ["https://ok.ru/videoembed/1825528678985"]}, {"title": "El Pitufo Aprendiz", "season": 1, "chapter": 8, "description": "", "sources": ["https://ok.ru/videoembed/1825529596489"]}, {"title": "El Pitufo Hechicero", "season": 1, "chapter": 9, "description": "", "sources": ["https://ok.ru/videoembed/1825527958089"]}, {"title": "El Pitufo Refugiado", "season": 1, "chapter": 10, "description": "", "sources": ["https://ok.ru/videoembed/1825527761481"]}, {"title": "El pitufo robot\u00edn", "season": 1, "chapter": 11, "description": "", "sources": ["https://ok.ru/videoembed/1825527827017"]}, {"title": "El Rey Pitufo", "season": 1, "chapter": 12, "description": "", "sources": ["https://ok.ru/videoembed/1825527892553"]}, {"title": "Gargamel El Generoso", "season": 1, "chapter": 13, "description": "", "sources": ["https://ok.ru/videoembed/1825528547913"]}, {"title": "La abominable bestia de las nieves", "season": 1, "chapter": 14, "description": "", "sources": ["https://ok.ru/videoembed/1825529006665"]}, {"title": "Pitufiasombrosa m\u00e1quina", "season": 1, "chapter": 15, "description": "", "sources": ["https://ok.ru/videoembed/1825528089161"]}, {"title": "Juventud", "season": 1, "chapter": 16, "description": "", "sources": ["https://ok.ru/videoembed/1825528875593"]}, {"title": "La Hechipituficera Hogata", "season": 1, "chapter": 17, "description": "", "sources": ["https://ok.ru/videoembed/1825529530953"]}, {"title": "La Mixtura amplificadora", "season": 1, "chapter": 18, "description": "", "sources": ["https://ok.ru/videoembed/1825528154697"]}, {"title": "La Pitufina", "season": 1, "chapter": 19, "description": "", "sources": ["https://ok.ru/videoembed/1825529334345"]}, {"title": "Las zapatillas de Pitufina", "season": 1, "chapter": 20, "description": "", "sources": ["https://ok.ru/videoembed/1825528482377"]}, {"title": "Los Comediantes", "season": 1, "chapter": 21, "description": "", "sources": ["https://ok.ru/videoembed/1825528744521"]}, {"title": "Los pitufos y el p\u00e1jaro Horripitufante", "season": 1, "chapter": 22, "description": "", "sources": ["https://ok.ru/videoembed/1825528613449"]}, {"title": "Los Pitufos y el \u00c1rbol de dinero", "season": 1, "chapter": 23, "description": "", "sources": ["https://ok.ru/videoembed/1825528941129"]}, {"title": "Los poderes de Pap\u00e1 Pitufo", "season": 1, "chapter": 24, "description": "", "sources": ["https://ok.ru/videoembed/1825529203273"]}, {"title": "Paraiso Pitufo", "season": 1, "chapter": 25, "description": "", "sources": ["https://ok.ru/videoembed/1825528810057"]}, {"title": "Pitufina y el Drag\u00f3n", "season": 1, "chapter": 26, "description": "", "sources": ["https://ok.ru/videoembed/1825529399881"]}, {"title": "Poeta y Pintor", "season": 1, "chapter": 27, "description": "", "sources": ["https://ok.ru/videoembed/1825528416841"]}, {"title": "Romeo y Pitufeta", "season": 1, "chapter": 28, "description": "", "sources": ["https://ok.ru/videoembed/1825528285769"]}, {"title": "Sir Fortach\u00f3n", "season": 1, "chapter": 29, "description": "", "sources": ["https://ok.ru/videoembed/1825528220233"]}, {"title": "Superpitufo", "season": 1, "chapter": 30, "description": "", "sources": ["https://ok.ru/videoembed/1825529465417"]}, {"title": "Bien esta lo que bien acaba", "season": 2, "chapter": 1, "description": "", "sources": ["https://ok.ru/videoembed/1825594477129"]}, {"title": "De que est\u00e1n hecho los sue\u00f1os", "season": 2, "chapter": 2, "description": "", "sources": ["https://ok.ru/videoembed/1825593952841"]}, {"title": "Educando a Goloso", "season": 2, "chapter": 3, "description": "", "sources": ["https://ok.ru/videoembed/1825593559625"]}, {"title": "El buen vecino pitufo", "season": 2, "chapter": 4, "description": "", "sources": ["https://ok.ru/videoembed/1825594280521"]}, {"title": "El Bueno el malo y el Pitufo", "season": 2, "chapter": 5, "description": "", "sources": ["https://ok.ru/videoembed/1825593297481"]}, {"title": "El cielo se esta cayendo", "season": 2, "chapter": 6, "description": "", "sources": ["https://ok.ru/videoembed/1825593363017"]}, {"title": "El peque\u00f1o gigante", "season": 2, "chapter": 7, "description": "", "sources": ["https://ok.ru/videoembed/1825593100873"]}, {"title": "El pitufo que no pod\u00eda decir que no", "season": 2, "chapter": 8, "description": "", "sources": ["https://ok.ru/videoembed/1825594608201"]}, {"title": "El Pitufo Renegado", "season": 2, "chapter": 9, "description": "", "sources": ["https://ok.ru/videoembed/1825593821769"]}, {"title": "El primer Telepitufo", "season": 2, "chapter": 10, "description": "", "sources": ["https://ok.ru/videoembed/1825594346057"]}, {"title": "La Amiga de Pitufina", "season": 2, "chapter": 11, "description": "", "sources": ["https://ok.ru/videoembed/1825594870345"]}, {"title": "La brigada de los pitufos", "season": 2, "chapter": 12, "description": "", "sources": ["https://ok.ru/videoembed/1825593231945"]}, {"title": "La Burbuja de Miedoso", "season": 2, "chapter": 13, "description": "", "sources": ["https://ok.ru/videoembed/1825594804809"]}, {"title": "La Ciudad Perdida de Yore", "season": 2, "chapter": 14, "description": "", "sources": ["https://ok.ru/videoembed/1825593035337"]}, {"title": "La formula aniquiladora", "season": 2, "chapter": 15, "description": "", "sources": ["https://ok.ru/videoembed/1825594214985"]}, {"title": "La Plaga Azul", "season": 2, "chapter": 16, "description": "", "sources": ["https://ok.ru/videoembed/1825594083913"]}, {"title": "La varita m\u00e1gica", "season": 2, "chapter": 17, "description": "", "sources": ["https://ok.ru/videoembed/1825593756233"]}, {"title": "La venganza de Los Pitufos", "season": 2, "chapter": 18, "description": "", "sources": ["https://ok.ru/videoembed/1825594018377"]}, {"title": "Las aventuras del Robin Pitufo", "season": 2, "chapter": 19, "description": "", "sources": ["https://ok.ru/videoembed/1825593887305"]}, {"title": "Los Pitufos Celestiales", "season": 2, "chapter": 20, "description": "", "sources": ["https://ok.ru/videoembed/1825594935881"]}, {"title": "Los Tres Pitufos Mosqueteros", "season": 2, "chapter": 21, "description": "", "sources": ["https://ok.ru/videoembed/1825593690697"]}, {"title": "No desperdicies Pitufo_Los Pitufos Helados", "season": 2, "chapter": 22, "description": "", "sources": ["https://ok.ru/videoembed/1825594542665"]}, {"title": "No quiero flores", "season": 2, "chapter": 23, "description": "", "sources": ["https://ok.ru/videoembed/1825594411593"]}, {"title": "Pitufo Dormil\u00f3n", "season": 2, "chapter": 24, "description": "", "sources": ["https://ok.ru/videoembed/1825594149449"]}, {"title": "Pitufos al Mar", "season": 2, "chapter": 25, "description": "", "sources": ["https://ok.ru/videoembed/1825593625161"]}, {"title": "Poema al tiempo", "season": 2, "chapter": 26, "description": "", "sources": ["https://ok.ru/videoembed/1825593428553"]}, {"title": "Por amor a Gargamel", "season": 2, "chapter": 27, "description": "", "sources": ["https://ok.ru/videoembed/1825594739273"]}, {"title": "Torpe adivina el futuro", "season": 2, "chapter": 28, "description": "", "sources": ["https://ok.ru/videoembed/1825593494089"]}, {"title": "Una buena acci\u00f3n merece otra", "season": 2, "chapter": 29, "description": "", "sources": ["https://ok.ru/videoembed/1825594673737"]}, {"title": "Una buena acci\u00f3n merece otra", "season": 2, "chapter": 30, "description": "", "sources": ["https://ok.ru/videoembed/1825595001417"]}, {"title": "\u00bfComo hacer un Arcoiris?", "season": 2, "chapter": 31, "description": "", "sources": ["https://ok.ru/videoembed/1825595066953"]}, {"title": "Armon\u00eda,  La estrella de la funci\u00f3n", "season": 3, "chapter": 1, "description": "", "sources": ["https://ok.ru/videoembed/1825725549129"]}, {"title": "A todas las criaturas grandes y peque\u00f1as", "season": 3, "chapter": 2, "description": "", "sources": ["https://ok.ru/videoembed/1825723386441"]}, {"title": "De tal palo tal astilla", "season": 3, "chapter": 3, "description": "", "sources": ["https://ok.ru/videoembed/1825724893769"]}, {"title": "Dilo por ti mismo Granjero", "season": 3, "chapter": 4, "description": "", "sources": ["https://ok.ru/videoembed/1825723124297"]}, {"title": "Dond\u00e9 est\u00e1 Beb\u00e9 Pitufo?", "season": 3, "chapter": 5, "description": "", "sources": ["https://ok.ru/videoembed/1825724762697"]}, {"title": "D\u00eda de los inocentes", "season": 3, "chapter": 6, "description": "", "sources": ["https://ok.ru/videoembed/1825723583049"]}, {"title": "El Ciervo Noble", "season": 3, "chapter": 7, "description": "", "sources": ["https://ok.ru/videoembed/1825725483593"]}, {"title": "El coraz\u00f3n de Fortach\u00f3n", "season": 3, "chapter": 8, "description": "", "sources": ["https://ok.ru/videoembed/1825725090377"]}, {"title": "El curandero Milagroso", "season": 3, "chapter": 9, "description": "", "sources": ["https://ok.ru/videoembed/1825725352521"]}, {"title": "El gorro de Vanidoso", "season": 3, "chapter": 10, "description": "", "sources": ["https://ok.ru/videoembed/1825725286985"]}, {"title": "El huevo podrido", "season": 3, "chapter": 11, "description": "", "sources": ["https://ok.ru/videoembed/1825724828233"]}, {"title": "El mago alado", "season": 3, "chapter": 12, "description": "", "sources": ["https://ok.ru/videoembed/1825725155913"]}, {"title": "El Pitufo que queria ser rey", "season": 3, "chapter": 13, "description": "", "sources": ["https://ok.ru/videoembed/1825725614665"]}, {"title": "El Premio pitufo de oro", "season": 3, "chapter": 14, "description": "", "sources": ["https://ok.ru/videoembed/1825723189833"]}, {"title": "El Pr\u00edncipe azul de Hogata", "season": 3, "chapter": 15, "description": "", "sources": ["https://ok.ru/videoembed/1825725745737"]}, {"title": "Especial de Halloween", "season": 3, "chapter": 16, "description": "", "sources": ["https://ok.ru/videoembed/1825723255369"]}, {"title": "Goloso y el Estofado m\u00e1gico", "season": 3, "chapter": 17, "description": "", "sources": ["https://ok.ru/videoembed/1825724631625"]}, {"title": "Habia una vez una luna azul", "season": 3, "chapter": 18, "description": "", "sources": ["https://ok.ru/videoembed/1825723779657"]}, {"title": "Hay que atrapar al Ladr\u00f3n", "season": 3, "chapter": 19, "description": "", "sources": ["https://ok.ru/videoembed/1825724500553"]}, {"title": "La Belleza es Superficial", "season": 3, "chapter": 20, "description": "", "sources": ["https://ok.ru/videoembed/1825723910729"]}, {"title": "La Busqueda de la piedra m\u00e1gica", "season": 3, "chapter": 21, "description": "", "sources": ["https://ok.ru/videoembed/1825724369481"]}, {"title": "La Capsula del tiempo de Los Pitufos", "season": 3, "chapter": 22, "description": "", "sources": ["https://ok.ru/videoembed/1825724959305"]}, {"title": "La Flor del Olvido", "season": 3, "chapter": 23, "description": "", "sources": ["https://ok.ru/videoembed/1825724435017"]}, {"title": "La Fuerza de Voluntad", "season": 3, "chapter": 24, "description": "", "sources": ["https://ok.ru/videoembed/1825723517513"]}, {"title": "La l\u00e1grima de un pitufo", "season": 3, "chapter": 25, "description": "", "sources": ["https://ok.ru/videoembed/1825723845193"]}, {"title": "La mejor memoria de la Aldea", "season": 3, "chapter": 26, "description": "", "sources": ["https://ok.ru/videoembed/1848891476553"]}, {"title": "La Novia del Genio", "season": 3, "chapter": 27, "description": "", "sources": ["https://ok.ru/videoembed/1825724238409"]}, {"title": "La primera Navidad del Beb\u00e9 Pitufo (Especial de Navidad II)", "season": 3, "chapter": 28, "description": "", "sources": ["https://ok.ru/videoembed/1825725680201"]}, {"title": "La sonaja m\u00e1gica", "season": 3, "chapter": 29, "description": "", "sources": ["https://ok.ru/videoembed/1825724107337"]}, {"title": "Las ultimas pitufresas silvestres", "season": 3, "chapter": 30, "description": "", "sources": ["https://ok.ru/videoembed/1825724041801"]}, {"title": "Lenguaje a Se\u00f1as", "season": 3, "chapter": 31, "description": "", "sources": ["https://ok.ru/videoembed/1825724566089"]}, {"title": "Pitufina por un D\u00eda", "season": 3, "chapter": 32, "description": "", "sources": ["https://ok.ru/videoembed/1825725024841"]}, {"title": "Pitufos Le\u00f1adores", "season": 3, "chapter": 33, "description": "", "sources": ["https://ok.ru/videoembed/1825724172873"]}, {"title": "Que suerte tan torpe", "season": 3, "chapter": 34, "description": "", "sources": ["https://ok.ru/videoembed/1825724697161"]}, {"title": "Todo retrato tiene una historia", "season": 3, "chapter": 35, "description": "", "sources": ["https://ok.ru/videoembed/1825723451977"]}, {"title": "Un abrazo para Gru\u00f1\u00f3n", "season": 3, "chapter": 36, "description": "", "sources": ["https://ok.ru/videoembed/1825724303945"]}, {"title": "Una campana para Azrael", "season": 3, "chapter": 37, "description": "", "sources": ["https://ok.ru/videoembed/1825723648585"]}, {"title": "Una choza no es un hogar", "season": 3, "chapter": 38, "description": "", "sources": ["https://ok.ru/videoembed/1825723714121"]}, {"title": "Un poco de auto confianza pitufo", "season": 3, "chapter": 39, "description": "", "sources": ["https://ok.ru/videoembed/1825723976265"]}, {"title": "Un regalo para el D\u00eda de Pap\u00e1 Pitufo", "season": 3, "chapter": 40, "description": "", "sources": ["https://ok.ru/videoembed/1825725418057"]}, {"title": "Desayuno con Goloso", "season": 4, "chapter": 1, "description": "", "sources": ["https://ok.ru/videoembed/1826069023305"]}, {"title": "El amigo m\u00e1s pitufo", "season": 4, "chapter": 2, "description": "", "sources": ["https://ok.ru/videoembed/1826068105801"]}, {"title": "El amigo m\u00e1s pitufo", "season": 4, "chapter": 3, "description": "", "sources": ["https://ok.ru/videoembed/1826068236873"]}, {"title": "El caballito alado", "season": 4, "chapter": 4, "description": "", "sources": ["https://ok.ru/videoembed/1826069809737"]}, {"title": "El Carnaval de Oto\u00f1o", "season": 4, "chapter": 5, "description": "", "sources": ["https://ok.ru/videoembed/1826069154377"]}, {"title": "El castillo de las Disputas", "season": 4, "chapter": 6, "description": "", "sources": ["https://ok.ru/videoembed/1826068892233"]}, {"title": "El dulce diente de Pitufina", "season": 4, "chapter": 7, "description": "", "sources": ["https://ok.ru/videoembed/1826068367945"]}, {"title": "El gigante de Gargamel", "season": 4, "chapter": 8, "description": "", "sources": ["https://ok.ru/videoembed/1826068630089"]}, {"title": "El hombre en la Luna", "season": 4, "chapter": 9, "description": "", "sources": ["https://ok.ru/videoembed/1826068171337"]}, {"title": "El Huesito alegre de Bromista", "season": 4, "chapter": 10, "description": "", "sources": ["https://ok.ru/videoembed/1826070006345"]}, {"title": "El incre\u00edble hechizo", "season": 4, "chapter": 11, "description": "", "sources": ["https://ok.ru/videoembed/1826069416521"]}, {"title": "El Oso Parches", "season": 4, "chapter": 12, "description": "", "sources": ["https://ok.ru/videoembed/1826068433481"]}, {"title": "El Pa\u00f1al Encantado", "season": 4, "chapter": 13, "description": "", "sources": ["https://ok.ru/videoembed/1826069088841"]}, {"title": "El Pitufador Pitufom\u00e1tico", "season": 4, "chapter": 14, "description": "", "sources": ["https://ok.ru/videoembed/1826068302409"]}, {"title": "El Pitufo Amo", "season": 4, "chapter": 15, "description": "", "sources": ["https://ok.ru/videoembed/1826068957769"]}, {"title": "El Pitufo de Troya", "season": 4, "chapter": 16, "description": "", "sources": ["https://ok.ru/videoembed/1826069678665"]}, {"title": "El Pitufo Gigant\u00f3n", "season": 4, "chapter": 17, "description": "", "sources": ["https://ok.ru/videoembed/1826069940809"]}, {"title": "El Regreso de Ojos Azules", "season": 4, "chapter": 18, "description": "", "sources": ["https://ok.ru/videoembed/1826068826697"]}, {"title": "El tiempo corre pitufos", "season": 4, "chapter": 19, "description": "", "sources": ["https://ok.ru/videoembed/1826068695625"]}, {"title": "El Viajero", "season": 4, "chapter": 20, "description": "", "sources": ["https://ok.ru/videoembed/1826069613129"]}, {"title": "El \u00c1rbol de los Deseos", "season": 4, "chapter": 21, "description": "", "sources": ["https://ok.ru/videoembed/1826069482057"]}, {"title": "La Aguja M\u00e1gica de Sastre", "season": 4, "chapter": 22, "description": "", "sources": ["https://ok.ru/videoembed/1826068761161"]}, {"title": "La Caballera Dorada de Pitufina", "season": 4, "chapter": 23, "description": "", "sources": ["https://ok.ru/videoembed/1826069875273"]}, {"title": "La Carrera de Los Pitufos", "season": 4, "chapter": 24, "description": "", "sources": ["https://ok.ru/videoembed/1826069219913"]}, {"title": "La desgracia de Gargamel", "season": 4, "chapter": 25, "description": "", "sources": ["https://ok.ru/videoembed/1826069350985"]}, {"title": "La Epidemia de la Tos Saltarina", "season": 4, "chapter": 26, "description": "", "sources": ["https://ok.ru/videoembed/1826068499017"]}, {"title": "La fuente de sopas", "season": 4, "chapter": 27, "description": "", "sources": ["https://ok.ru/videoembed/1826068564553"]}, {"title": "La sombra de Bromista", "season": 4, "chapter": 28, "description": "", "sources": ["https://ok.ru/videoembed/1826145700425"]}, {"title": "Las nuevas colinas pitufo", "season": 4, "chapter": 29, "description": "", "sources": ["https://ok.ru/videoembed/1848907205193"]}, {"title": "Las verrugas de Pap\u00e1 Pitufo", "season": 4, "chapter": 30, "description": "", "sources": ["https://ok.ru/videoembed/1826145503817"]}, {"title": "Los duendecillos", "season": 4, "chapter": 31, "description": "", "sources": ["https://ok.ru/videoembed/1826144586313"]}, {"title": "Los Pitufos de jingibre", "season": 4, "chapter": 32, "description": "", "sources": ["https://ok.ru/videoembed/1826145634889"]}, {"title": "Los Pitufos Monstruosos", "season": 4, "chapter": 33, "description": "", "sources": ["https://ok.ru/videoembed/1826144913993"]}, {"title": "Los Visitantes", "season": 4, "chapter": 34, "description": "", "sources": ["https://ok.ru/videoembed/1826145372745"]}, {"title": "Narices Nuevas", "season": 4, "chapter": 35, "description": "", "sources": ["https://ok.ru/videoembed/1826145045065"]}, {"title": "Nunca lo dejes para Ma\u00f1ana", "season": 4, "chapter": 36, "description": "", "sources": ["https://ok.ru/videoembed/1826144520777"]}, {"title": "Perdido en el pantano de las sombras", "season": 4, "chapter": 37, "description": "", "sources": ["https://ok.ru/videoembed/1826145569353"]}, {"title": "Pitufina y Fortach\u00f3n", "season": 4, "chapter": 38, "description": "", "sources": ["https://ok.ru/videoembed/1826144979529"]}, {"title": "Pitufos de Piedra", "season": 4, "chapter": 39, "description": "", "sources": ["https://ok.ru/videoembed/1826145241673"]}, {"title": "Pitufos y s\u00f3lo pitufos", "season": 4, "chapter": 40, "description": "", "sources": ["https://ok.ru/videoembed/1826145176137"]}, {"title": "Pon la otra mejilla", "season": 4, "chapter": 41, "description": "", "sources": ["https://ok.ru/videoembed/1826144848457"]}, {"title": "Simbolos de Sabidur\u00eda", "season": 4, "chapter": 42, "description": "", "sources": ["https://ok.ru/videoembed/1826145307209"]}, {"title": "Una Fiesta de Pijamas para Perezoso", "season": 4, "chapter": 43, "description": "", "sources": ["https://ok.ru/videoembed/1826145110601"]}, {"title": "Una mascota para el Beb\u00e9", "season": 4, "chapter": 44, "description": "", "sources": ["https://ok.ru/videoembed/1826144717385"]}, {"title": "Un beb\u00e9 ante su majestad", "season": 4, "chapter": 45, "description": "", "sources": ["https://ok.ru/videoembed/1826145438281"]}, {"title": "Un circo para el Beb\u00e9", "season": 4, "chapter": 46, "description": "", "sources": ["https://ok.ru/videoembed/1826144782921"]}, {"title": "Aquel que r\u00eda el \u00faltimo", "season": 5, "chapter": 1, "description": "", "sources": ["https://ok.ru/videoembed/1826162018889"]}, {"title": "Cachorro", "season": 5, "chapter": 2, "description": "", "sources": ["https://ok.ru/videoembed/1826161363529"]}, {"title": "Cosas que Pitufan en la noche", "season": 5, "chapter": 3, "description": "", "sources": ["https://ok.ru/videoembed/1826161560137"]}, {"title": "Educando a Gigant\u00f3n", "season": 5, "chapter": 4, "description": "", "sources": ["https://ok.ru/videoembed/1826161429065"]}, {"title": "El Album Familiar de Pap\u00e1 Pitufo", "season": 5, "chapter": 5, "description": "", "sources": ["https://ok.ru/videoembed/1826161101385"]}, {"title": "El amigo de Gigant\u00f3n", "season": 5, "chapter": 6, "description": "", "sources": ["https://ok.ru/videoembed/1826161494601"]}, {"title": "El Dia libre de Pap\u00e1 Pitufo", "season": 5, "chapter": 7, "description": "", "sources": ["https://ok.ru/videoembed/1826161691209"]}, {"title": "El d\u00eda de la Infelicidad", "season": 5, "chapter": 8, "description": "", "sources": ["https://ok.ru/videoembed/1826161822281"]}, {"title": "El Extra\u00f1o Conjuro", "season": 5, "chapter": 9, "description": "", "sources": ["https://ok.ru/videoembed/1826161756745"]}, {"title": "El mejor jugador del Pueblo", "season": 5, "chapter": 10, "description": "", "sources": ["https://ok.ru/videoembed/1826161953353"]}, {"title": "El monstruo de las cavernas", "season": 5, "chapter": 11, "description": "", "sources": ["https://ok.ru/videoembed/1826161166921"]}, {"title": "El Pitufo Enmascarado", "season": 5, "chapter": 12, "description": "", "sources": ["https://ok.ru/videoembed/1826161232457"]}, {"title": "Fil\u00f3sofo, El Amigo De Todos Los Animales", "season": 5, "chapter": 13, "description": "", "sources": ["https://ok.ru/videoembed/1826161297993"]}, {"title": "La Cama voladora de Pap\u00e1 Pitufo", "season": 5, "chapter": 14, "description": "", "sources": ["https://ok.ru/videoembed/1826161625673"]}, {"title": "La crisis del Fango", "season": 5, "chapter": 15, "description": "", "sources": ["https://ok.ru/videoembed/1826161887817"]}, {"title": "La Fiesta de Fil\u00f3sofo", "season": 5, "chapter": 16, "description": "", "sources": ["https://ok.ru/videoembed/1826162149961"]}, {"title": "\u00a1Alarma, Pitufos!", "season": 5, "chapter": 17, "description": "", "sources": ["https://ok.ru/videoembed/1826162084425"]}, {"title": "Don Pituzorro", "season": 6, "chapter": 1, "description": "", "sources": ["https://ok.ru/videoembed/1826206321225"]}, {"title": "Educando a Cachorro", "season": 6, "chapter": 2, "description": "", "sources": ["https://ok.ru/videoembed/1826206124617"]}, {"title": "El Abuelo Pitufo Parte 1", "season": 6, "chapter": 3, "description": "", "sources": ["https://ok.ru/videoembed/1826205207113"]}, {"title": "El Abuelo Pitufo Parte 2", "season": 6, "chapter": 4, "description": "", "sources": ["https://ok.ru/videoembed/1826205993545"]}, {"title": "El Abuelo Pitufo Parte 3", "season": 6, "chapter": 5, "description": "", "sources": ["https://ok.ru/videoembed/1826205469257"]}, {"title": "El capricho de Travieso", "season": 6, "chapter": 6, "description": "", "sources": ["https://ok.ru/videoembed/1826205862473"]}, {"title": "El doctor malo y el se\u00f1or amable", "season": 6, "chapter": 7, "description": "", "sources": ["https://ok.ru/videoembed/1826205731401"]}, {"title": "El flechazo de Hogatha (Especial de San Valent\u00edn II)", "season": 6, "chapter": 8, "description": "", "sources": ["https://ok.ru/videoembed/1826205076041"]}, {"title": "El Pitufo Galante", "season": 6, "chapter": 9, "description": "", "sources": ["https://ok.ru/videoembed/1826205010505"]}, {"title": "Gru\u00f1\u00f3n va a Chapotear", "season": 6, "chapter": 10, "description": "", "sources": ["https://ok.ru/videoembed/1826205534793"]}, {"title": "Gru\u00f1\u00f3n va a Chapotear", "season": 6, "chapter": 11, "description": "", "sources": ["https://ok.ru/videoembed/1826206190153"]}, {"title": "La Esfera m\u00e1gica", "season": 6, "chapter": 12, "description": "", "sources": ["https://ok.ru/videoembed/1826206255689"]}, {"title": "La Esfera m\u00e1gica", "season": 6, "chapter": 13, "description": "", "sources": ["https://ok.ru/videoembed/1826206386761"]}, {"title": "La Flor de Pitufina", "season": 6, "chapter": 14, "description": "", "sources": ["https://ok.ru/videoembed/1826206452297"]}, {"title": "La Pluma Encantada", "season": 6, "chapter": 15, "description": "", "sources": ["https://ok.ru/videoembed/1826205141577"]}, {"title": "La Raiz del Mal", "season": 6, "chapter": 16, "description": "", "sources": ["https://ok.ru/videoembed/1826205796937"]}, {"title": "La Raiz del Mal", "season": 6, "chapter": 17, "description": "", "sources": ["https://ok.ru/videoembed/1826205338185"]}, {"title": "Llamando al Doctor Pitufo", "season": 6, "chapter": 18, "description": "", "sources": ["https://ok.ru/videoembed/1826205665865"]}, {"title": "Los Pitufos Bomberos", "season": 6, "chapter": 19, "description": "", "sources": ["https://ok.ru/videoembed/1826205600329"]}, {"title": "Pajaro Parlach\u00edn", "season": 6, "chapter": 20, "description": "", "sources": ["https://ok.ru/videoembed/1826205272649"]}, {"title": "Sassette aprende a leer", "season": 6, "chapter": 21, "description": "", "sources": ["https://ok.ru/videoembed/1826206059081"]}, {"title": "Viaje al Pitufo de la Tierra", "season": 6, "chapter": 22, "description": "", "sources": ["https://ok.ru/videoembed/1826205928009"]}, {"title": "Yo pitufo a los arboles", "season": 6, "chapter": 23, "description": "", "sources": ["https://ok.ru/videoembed/1826205403721"]}, {"title": "Como acu\u00f1ar Pitufos", "season": 7, "chapter": 1, "description": "", "sources": ["https://ok.ru/videoembed/1826235091529"]}, {"title": "El Costal m\u00e1gico de Santa Claus (Especial de Navidad III)", "season": 7, "chapter": 2, "description": "", "sources": ["https://ok.ru/videoembed/1826235877961"]}, {"title": "El gran amor de Clorhidiris", "season": 7, "chapter": 3, "description": "", "sources": ["https://ok.ru/videoembed/1826235550281"]}, {"title": "El libro de bromas de Bromista", "season": 7, "chapter": 4, "description": "", "sources": ["https://ok.ru/videoembed/1826235419209"]}, {"title": "El mago m\u00e1s rapido del mundo", "season": 7, "chapter": 5, "description": "", "sources": ["https://ok.ru/videoembed/1826234567241"]}, {"title": "El mejor amigo de Vanidoso", "season": 7, "chapter": 6, "description": "", "sources": ["https://ok.ru/videoembed/1826234501705"]}, {"title": "El peque\u00f1o Pitufo Gigante", "season": 7, "chapter": 7, "description": "", "sources": ["https://ok.ru/videoembed/1826234894921"]}, {"title": "locomotor", "season": 7, "chapter": 8, "description": "", "sources": ["https://ok.ru/videoembed/1826234632777"]}, {"title": "El Pitufo Nadie", "season": 7, "chapter": 9, "description": "", "sources": ["https://ok.ru/videoembed/1826236009033"]}, {"title": "El pitufo que todo lo hac\u00eda bien", "season": 7, "chapter": 10, "description": "", "sources": ["https://ok.ru/videoembed/1826235288137"]}, {"title": "El Pitufo Salvaje Parte 1", "season": 7, "chapter": 11, "description": "", "sources": ["https://ok.ru/videoembed/1826236140105"]}, {"title": "El Pitufo Tenor", "season": 7, "chapter": 12, "description": "", "sources": ["https://ok.ru/videoembed/1826235812425"]}, {"title": "La Capa de Bromista", "season": 7, "chapter": 13, "description": "", "sources": ["https://ok.ru/videoembed/1826235353673"]}, {"title": "La Escrupulosa aventura de Guillerm\u00edn", "season": 7, "chapter": 14, "description": "", "sources": ["https://ok.ru/videoembed/1826234960457"]}, {"title": "La mala suerte de Los Pitufos", "season": 7, "chapter": 15, "description": "", "sources": ["https://ok.ru/videoembed/1826234763849"]}, {"title": "La mascota de los pitufos", "season": 7, "chapter": 16, "description": "", "sources": ["https://ok.ru/videoembed/1826235615817"]}, {"title": "La Orquesta de Los Pitufos", "season": 7, "chapter": 17, "description": "", "sources": ["https://ok.ru/videoembed/1826235222601"]}, {"title": "La peligrosa amistad de Sassette", "season": 7, "chapter": 18, "description": "", "sources": ["https://ok.ru/videoembed/1826235484745"]}, {"title": "La segunda infancia de Gargamel", "season": 7, "chapter": 19, "description": "", "sources": ["https://ok.ru/videoembed/1826235943497"]}, {"title": "Loco por Pitufina", "season": 7, "chapter": 20, "description": "", "sources": ["https://ok.ru/videoembed/1826234698313"]}, {"title": "Los Pitufos Desvelados", "season": 7, "chapter": 21, "description": "", "sources": ["https://ok.ru/videoembed/1826236074569"]}, {"title": "Los Pitufos Naufragos", "season": 7, "chapter": 22, "description": "", "sources": ["https://ok.ru/videoembed/1826234829385"]}, {"title": "Pitufianimas", "season": 7, "chapter": 23, "description": "", "sources": ["https://ok.ru/videoembed/1826235746889"]}, {"title": "Pitufina en Mal Estado", "season": 7, "chapter": 24, "description": "", "sources": ["https://ok.ru/videoembed/1826235157065"]}, {"title": "Pitufo hoyo en uno", "season": 7, "chapter": 25, "description": "", "sources": ["https://ok.ru/videoembed/1826235025993"]}, {"title": "El Bast\u00f3n del Abuelo", "season": 8, "chapter": 1, "description": "", "sources": ["https://ok.ru/videoembed/1826269039177"]}, {"title": "El Camino de Nanny", "season": 8, "chapter": 2, "description": "", "sources": ["https://ok.ru/videoembed/1826269235785"]}, {"title": "El merito del Abuelo Pitufo", "season": 8, "chapter": 3, "description": "", "sources": ["https://ok.ru/videoembed/1826269956681"]}, {"title": "El Retorno de Nemesis", "season": 8, "chapter": 4, "description": "", "sources": ["https://ok.ru/videoembed/1826269301321"]}, {"title": "La Fiesta de Denisa", "season": 8, "chapter": 5, "description": "", "sources": ["https://ok.ru/videoembed/1826269170249"]}, {"title": "La mansi\u00f3n de los Espejos", "season": 8, "chapter": 6, "description": "", "sources": ["https://ok.ru/videoembed/1826269825609"]}, {"title": "La Mu\u00f1equita de Denisa", "season": 8, "chapter": 7, "description": "", "sources": ["https://ok.ru/videoembed/1826269497929"]}, {"title": "La Nana Perdida", "season": 8, "chapter": 8, "description": "", "sources": ["https://ok.ru/videoembed/1826269366857"]}, {"title": "La Sandia M\u00e1gica", "season": 8, "chapter": 9, "description": "", "sources": ["https://ok.ru/videoembed/1826269432393"]}, {"title": "Los Invitados Inesperados de Don Pitufo", "season": 8, "chapter": 10, "description": "", "sources": ["https://ok.ru/videoembed/1826269760073"]}, {"title": "M\u00e1s vale malo por conocido", "season": 8, "chapter": 11, "description": "", "sources": ["https://ok.ru/videoembed/1826270022217"]}, {"title": "Ni\u00f1eras Chapuseras", "season": 8, "chapter": 12, "description": "", "sources": ["https://ok.ru/videoembed/1826269563465"]}, {"title": "Pituforobotin Electrizado", "season": 8, "chapter": 13, "description": "", "sources": ["https://ok.ru/videoembed/1826269891145"]}, {"title": "Pitufos en Primera plana", "season": 8, "chapter": 14, "description": "", "sources": ["https://ok.ru/videoembed/1826269104713"]}, {"title": "Tont\u00edn el excursionista", "season": 8, "chapter": 15, "description": "", "sources": ["https://ok.ru/videoembed/1826269629001"]}, {"title": "Una casa para Nanny", "season": 8, "chapter": 16, "description": "", "sources": ["https://ok.ru/videoembed/1826269694537"]}, {"title": "Ali Beb\u00e9 y sus mocosos", "season": 9, "chapter": 1, "description": "", "sources": ["https://ok.ru/videoembed/1826299316809"]}, {"title": "Buena Suerte Smoogle", "season": 9, "chapter": 2, "description": "", "sources": ["https://ok.ru/videoembed/1826300955209"]}, {"title": "El dedo verde de Pitufina", "season": 9, "chapter": 3, "description": "", "sources": ["https://ok.ru/videoembed/1826301217353"]}, {"title": "El fantasma gaitero", "season": 9, "chapter": 4, "description": "", "sources": ["https://ok.ru/videoembed/1826300168777"]}, {"title": "El genio tonto", "season": 9, "chapter": 5, "description": "", "sources": ["https://ok.ru/videoembed/1826300627529"]}, {"title": "El gran sue\u00f1o de Pap\u00e1 Pitufo", "season": 9, "chapter": 6, "description": "", "sources": ["https://ok.ru/videoembed/1826300365385"]}, {"title": "El Mosco del Valle", "season": 9, "chapter": 7, "description": "", "sources": ["https://ok.ru/videoembed/1826299120201"]}, {"title": "El Pitufo asustado (Especial de Halloween 2)", "season": 9, "chapter": 8, "description": "", "sources": ["https://ok.ru/videoembed/1826301020745"]}, {"title": "El Rinoceronte de Oro", "season": 9, "chapter": 9, "description": "", "sources": ["https://ok.ru/videoembed/1826299775561"]}, {"title": "Enamorada de Fortach\u00f3n", "season": 9, "chapter": 10, "description": "", "sources": ["https://ok.ru/videoembed/1826300889673"]}, {"title": "En el tiempo del olvido", "season": 9, "chapter": 11, "description": "", "sources": ["https://ok.ru/videoembed/1826299578953"]}, {"title": "Fil\u00f3sofo el hechicero", "season": 9, "chapter": 12, "description": "", "sources": ["https://ok.ru/videoembed/1826299972169"]}, {"title": "Fortach\u00f3n ve una serpiente", "season": 9, "chapter": 13, "description": "", "sources": ["https://ok.ru/videoembed/1826299447881"]}, {"title": "Hazlo o Pitufate", "season": 9, "chapter": 14, "description": "", "sources": ["https://ok.ru/videoembed/1826299185737"]}, {"title": "La fuente de la Juventud", "season": 9, "chapter": 15, "description": "", "sources": ["https://ok.ru/videoembed/1826301086281"]}, {"title": "La Pintura rusa de Pintor", "season": 9, "chapter": 16, "description": "", "sources": ["https://ok.ru/videoembed/1826301151817"]}, {"title": "Las Galletas de la Fortuna", "season": 9, "chapter": 17, "description": "", "sources": ["https://ok.ru/videoembed/1826300037705"]}, {"title": "Los Adorables Pitufos", "season": 9, "chapter": 18, "description": "", "sources": ["https://ok.ru/videoembed/1826301676105"]}, {"title": "Los Pitufos de la cabeza peque\u00f1a", "season": 9, "chapter": 19, "description": "", "sources": ["https://ok.ru/videoembed/1826301610569"]}, {"title": "Los Pitufos de la mesa redonda", "season": 9, "chapter": 20, "description": "", "sources": ["https://ok.ru/videoembed/1826300299849"]}, {"title": "Los Pitufos Troyanos", "season": 9, "chapter": 21, "description": "", "sources": ["https://ok.ru/videoembed/1826299644489"]}, {"title": "Los Pitufos y el emperador", "season": 9, "chapter": 22, "description": "", "sources": ["https://ok.ru/videoembed/1826299906633"]}, {"title": "Perdidos en el Tiempo", "season": 9, "chapter": 23, "description": "", "sources": ["https://ok.ru/videoembed/1826300758601"]}, {"title": "Pitufo Bucanero", "season": 9, "chapter": 24, "description": "", "sources": ["https://ok.ru/videoembed/1826300824137"]}, {"title": "Pitufo Cavern\u00edcola", "season": 9, "chapter": 25, "description": "", "sources": ["https://ok.ru/videoembed/1826299382345"]}, {"title": "Pitufo en Curry", "season": 9, "chapter": 26, "description": "", "sources": ["https://ok.ru/videoembed/1826299513417"]}, {"title": "Salvaje es un cuc\u00fa", "season": 9, "chapter": 27, "description": "", "sources": ["https://ok.ru/videoembed/1826301479497"]}, {"title": "Tont\u00edn Karateca", "season": 9, "chapter": 28, "description": "", "sources": ["https://ok.ru/videoembed/1826300693065"]}, {"title": "Un Pez llamado Travieso", "season": 9, "chapter": 29, "description": "", "sources": ["https://ok.ru/videoembed/1826300496457"]}, {"title": "Vanidoso no tiene Espejo", "season": 9, "chapter": 30, "description": "", "sources": ["https://ok.ru/videoembed/1826301413961"]}]